[{"input":{"walls":[139,139],"realWalls":[true,false],"utils":[{"Pos":4,"Wall":0,"Tag":"ventilation","Id":0},{"Pos":-1,"Wall":-1,"Tag":"canalization","Id":1},{"Pos":63,"Wall":0,"Tag":"window","Id":2},{"Pos":0,"Wall":0,"Tag":"entry","Id":3},{"Pos":-1,"Wall":-1,"Tag":"exit","Id":4}]},"output":[{"type":"C","subType":1,"wall":0,"width":60,"pos":0},{"type":"P","subType":0,"wall":0,"width":19,"pos":60},{"type":"W","subType":2,"wall":0,"width":60,"pos":79}]},{"input":{"walls":[152,152],"realWalls":[true,false],"utils":[{"Pos":107,"Wall":0,"Tag":"ventilation","Id":0},{"Pos":80,"Wall":0,"Tag":"canalization","Id":1},{"Pos":-1,"Wall":-1,"Tag":"window","Id":2},{"Pos":0,"Wall":0,"Tag":"entry","Id":3},{"Pos":-1,"Wall":-1,"Tag":"exit","Id":4}]},"output":[{"type":"P","subType":0,"wall":0,"width":32,"pos":0},{"type":"W","subType":2,"wall":0,"width":60,"pos":32},{"type":"C","subType":1,"wall":0,"width":60,"pos":92}]},{"input":{"walls":[240,240],"realWalls":[true,false],"utils":[{"Pos":36,"Wall":0,"Tag":"ventilation","Id":0},{"Pos":28,"Wall":0,"Tag":"canalization","Id":1},{"Pos":-1,"Wall":-1,"Tag":"window","Id":2},{"Pos":0,"Wall":0,"Tag":"entry","Id":3},{"Pos":-1,"Wall":-1,"Tag":"exit","Id":4}]},"output":[{"type":"W","subType":2,"wall":0,"width":60,"pos":0},{"type":"C","subType":2,"wall":0,"width":60,"pos":60},{"type":"P","subType":0,"wall":0,"width":60,"pos":120},{"type":"S","subType":2,"wall":0,"width":60,"pos":180}]},{"input":{"walls":[221,221],"realWalls":[true,false],"utils":[{"Pos":123,"Wall":0,"Tag":"ventilation","Id":0},{"Pos":-1,"Wall":-1,"Tag":"canalization","Id":1},{"Pos":-1,"Wall":-1,"Tag":"window","Id":2},{"Pos":0,"Wall":0,"Tag":"entry","Id":3},{"Pos":220,"Wall":0,"Tag":"exit","Id":4}]},"output":[{"type":"W","subType":2,"wall":0,"width":60,"pos":0},{"type":"P","subType":0,"wall":0,"width":41,"pos":60},{"type":"C","subType":2,"wall":0,"width":60,"pos":101},{"type":"S","subType":2,"wall":0,"width":60,"pos":161}]},{"input":{"walls":[406,406],"realWalls":[true,false],"utils":[{"Pos":168,"Wall":0,"Tag":"ventilation","Id":0},{"Pos":307,"Wall":0,"Tag":"canalization","Id":1},{"Pos":129,"Wall":0,"Tag":"window","Id":2},{"Pos":0,"Wall":0,"Tag":"entry","Id":3},{"Pos":-1,"Wall":-1,"Tag":"exit","Id":4}]},"output":[{"type":"S","subType":3,"wall":0,"width":90,"pos":0},{"type":"P","subType":0,"wall":0,"width":60,"pos":90},{"type":"C","subType":2,"wall":0,"width":60,"pos":150},{"type":"P","subType":0,"wall":0,"width":76,"pos":210},{"type":"W","subType":3,"wall":0,"width":120,"pos":286}]},{"input":{"walls":[161,161],"realWalls":[true,false],"utils":[{"Pos":30,"Wall":0,"Tag":"ventilation","Id":0},{"Pos":-1,"Wall":-1,"Tag":"canalization","Id":1},{"Pos":-1,"Wall":-1,"Tag":"window","Id":2},{"Pos":0,"Wall":0,"Tag":"entry","Id":3},{"Pos":-1,"Wall":-1,"Tag":"exit","Id":4}]},"output":[{"type":"C","subType":1,"wall":0,"width":60,"pos":0},{"type":"P","subType":0,"wall":0,"width":41,"pos":60},{"type":"W","subType":2,"wall":0,"width":60,"pos":101}]},{"input":{"walls":[317,317],"realWalls":[true,false],"utils":[{"Pos":286,"Wall":0,"Tag":"ventilation","Id":0},{"Pos":-1,"Wall":-1,"Tag":"canalization","Id":1},{"Pos":-1,"Wall":-1,"Tag":"window","Id":2},{"Pos":0,"Wall":0,"Tag":"entry","Id":3},{"Pos":-1,"Wall":-1,"Tag":"exit","Id":4}]},"output":[{"type":"S","subType":3,"wall":0,"width":90,"pos":0},{"type":"W","subType":3,"wall":0,"width":120,"pos":90},{"type":"P","subType":0,"wall":0,"width":47,"pos":210},{"type":"C","subType":2,"wall":0,"width":60,"pos":257}]},{"input":{"walls":[505,505],"realWalls":[true,false],"utils":[{"Pos":-1,"Wall":-1,"Tag":"ventilation","Id":0},{"Pos":401,"Wall":0,"Tag":"canalization","Id":1},{"Pos":-1,"Wall":-1,"Tag":"window","Id":2},{"Pos":-1,"Wall":-1,"Tag":"entry","Id":3},{"Pos":503,"Wall":0,"Tag":"exit","Id":4}]},"output":[{"type":"S","subType":4,"wall":0,"width":120,"pos":0},{"type":"P","subType":0,"wall":0,"width":60,"pos":120},{"type":"C","subType":3,"wall":0,"width":120,"pos":180},{"type":"P","subType":0,"wall":0,"width":85,"pos":300},{"type":"W","subType":3,"wall":0,"width":120,"pos":385}]},{"input":{"walls":[456,456],"realWalls":[true,false],"utils":[{"Pos":158,"Wall":0,"Tag":"ventilation","Id":0},{"Pos":371,"Wall":0,"Tag":"canalization","Id":1},{"Pos":-1,"Wall":-1,"Tag":"window","Id":2},{"Pos":0,"Wall":0,"Tag":"entry","Id":3},{"Pos":456,"Wall":0,"Tag":"exit","Id":4}]},"output":[{"type":"S","subType":4,"wall":0,"width":120,"pos":0},{"type":"P","subType":0,"wall":0,"width":36,"pos":120},{"type":"C","subType":3,"wall":0,"width":120,"pos":156},{"type":"P","subType":0,"wall":0,"width":60,"pos":276},{"type":"W","subType":3,"wall":0,"width":120,"pos":336}]},{"input":{"walls":[415,415],"realWalls":[true,false],"utils":[{"Pos":253,"Wall":0,"Tag":"ventilation","Id":0},{"Pos":266,"Wall":0,"Tag":"canalization","Id":1},{"Pos":-1,"Wall":-1,"Tag":"window","Id":2},{"Pos":0,"Wall":0,"Tag":"entry","Id":3},{"Pos":-1,"Wall":-1,"Tag":"exit","Id":4}]},"output":[{"type":"S","subType":3,"wall":0,"width":90,"pos":0},{"type":"P","subType":0,"wall":0,"width":60,"pos":90},{"type":"W","subType":3,"wall":0,"width":120,"pos":150},{"type":"C","subType":2,"wall":0,"width":60,"pos":270},{"type":"P","subType":0,"wall":0,"width":85,"pos":330}]},{"input":{"walls":[464,464],"realWalls":[true,false],"utils":[{"Pos":461,"Wall":0,"Tag":"ventilation","Id":0},{"Pos":-1,"Wall":-1,"Tag":"canalization","Id":1},{"Pos":-1,"Wall":-1,"Tag":"window","Id":2},{"Pos":0,"Wall":0,"Tag":"entry","Id":3},{"Pos":-1,"Wall":-1,"Tag":"exit","Id":4}]},"output":[{"type":"S","subType":4,"wall":0,"width":120,"pos":0},{"type":"P","subType":0,"wall":0,"width":44,"pos":120},{"type":"W","subType":3,"wall":0,"width":120,"pos":164},{"type":"P","subType":0,"wall":0,"width":60,"pos":284},{"type":"C","subType":3,"wall":0,"width":120,"pos":344}]},{"input":{"walls":[246,246],"realWalls":[true,false],"utils":[{"Pos":102,"Wall":0,"Tag":"ventilation","Id":0},{"Pos":243,"Wall":0,"Tag":"canalization","Id":1},{"Pos":-1,"Wall":-1,"Tag":"window","Id":2},{"Pos":-1,"Wall":-1,"Tag":"entry","Id":3},{"Pos":-1,"Wall":-1,"Tag":"exit","Id":4}]},"output":[{"type":"S","subType":2,"wall":0,"width":60,"pos":0},{"type":"C","subType":2,"wall":0,"width":60,"pos":60},{"type":"P","subType":0,"wall":0,"width":66,"pos":120},{"type":"W","subType":2,"wall":0,"width":60,"pos":186}]},{"input":{"walls":[252,252],"realWalls":[true,false],"utils":[{"Pos":139,"Wall":0,"Tag":"ventilation","Id":0},{"Pos":-1,"Wall":-1,"Tag":"canalization","Id":1},{"Pos":-1,"Wall":-1,"Tag":"window","Id":2},{"Pos":0,"Wall":0,"Tag":"entry","Id":3},{"Pos":-1,"Wall":-1,"Tag":"exit","Id":4}]},"output":[{"type":"W","subType":2,"wall":0,"width":60,"pos":0},{"type":"P","subType":0,"wall":0,"width":72,"pos":60},{"type":"C","subType":2,"wall":0,"width":60,"pos":132},{"type":"S","subType":2,"wall":0,"width":60,"pos":192}]},{"input":{"walls":[474,474],"realWalls":[true,false],"utils":[{"Pos":265,"Wall":0,"Tag":"ventilation","Id":0},{"Pos":207,"Wall":0,"Tag":"canalization","Id":1},{"Pos":-1,"Wall":-1,"Tag":"window","Id":2},{"Pos":0,"Wall":0,"Tag":"entry","Id":3},{"Pos":-1,"Wall":-1,"Tag":"exit","Id":4}]},"output":[{"type":"S","subType":4,"wall":0,"width":120,"pos":0},{"type":"W","subType":3,"wall":0,"width":120,"pos":120},{"type":"C","subType":3,"wall":0,"width":120,"pos":240},{"type":"P","subType":0,"wall":0,"width":60,"pos":360},{"type":"P","subType":0,"wall":0,"width":54,"pos":420}]},{"input":{"walls":[474,474],"realWalls":[true,false],"utils":[{"Pos":265,"Wall":0,"Tag":"ventilation","Id":0},{"Pos":207,"Wall":0,"Tag":"canalization","Id":1},{"Pos":-1,"Wall":-1,"Tag":"window","Id":2},{"Pos":0,"Wall":0,"Tag":"entry","Id":3},{"Pos":-1,"Wall":-1,"Tag":"exit","Id":4}]},"output":[{"type":"S","subType":4,"wall":0,"width":120,"pos":0},{"type":"W","subType":3,"wall":0,"width":120,"pos":120},{"type":"C","subType":3,"wall":0,"width":120,"pos":240},{"type":"P","subType":0,"wall":0,"width":54,"pos":360},{"type":"P","subType":0,"wall":0,"width":60,"pos":414}]},{"input":{"walls":[472,472],"realWalls":[true,false],"utils":[{"Pos":59,"Wall":0,"Tag":"ventilation","Id":0},{"Pos":-1,"Wall":-1,"Tag":"canalization","Id":1},{"Pos":-1,"Wall":-1,"Tag":"window","Id":2},{"Pos":0,"Wall":0,"Tag":"entry","Id":3},{"Pos":471,"Wall":0,"Tag":"exit","Id":4}]},"output":[{"type":"C","subType":3,"wall":0,"width":120,"pos":0},{"type":"P","subType":0,"wall":0,"width":60,"pos":120},{"type":"W","subType":3,"wall":0,"width":120,"pos":180},{"type":"P","subType":0,"wall":0,"width":52,"pos":300},{"type":"S","subType":4,"wall":0,"width":120,"pos":352}]},{"input":{"walls":[175,175],"realWalls":[true,false],"utils":[{"Pos":49,"Wall":0,"Tag":"ventilation","Id":0},{"Pos":76,"Wall":0,"Tag":"canalization","Id":1},{"Pos":-1,"Wall":-1,"Tag":"window","Id":2},{"Pos":0,"Wall":0,"Tag":"entry","Id":3},{"Pos":-1,"Wall":-1,"Tag":"exit","Id":4}]},"output":[{"type":"C","subType":1,"wall":0,"width":60,"pos":0},{"type":"W","subType":2,"wall":0,"width":60,"pos":60},{"type":"P","subType":0,"wall":0,"width":55,"pos":120}]},{"input":{"walls":[488,488],"realWalls":[true,false],"utils":[{"Pos":321,"Wall":0,"Tag":"ventilation","Id":0},{"Pos":301,"Wall":0,"Tag":"canalization","Id":1},{"Pos":-1,"Wall":-1,"Tag":"window","Id":2},{"Pos":-1,"Wall":-1,"Tag":"entry","Id":3},{"Pos":-1,"Wall":-1,"Tag":"exit","Id":4}]},"output":[{"type":"S","subType":4,"wall":0,"width":120,"pos":0},{"type":"P","subType":0,"wall":0,"width":68,"pos":120},{"type":"W","subType":3,"wall":0,"width":120,"pos":188},{"type":"C","subType":3,"wall":0,"width":120,"pos":308},{"type":"P","subType":0,"wall":0,"width":60,"pos":428}]},{"input":{"walls":[477,477],"realWalls":[true,false],"utils":[{"Pos":190,"Wall":0,"Tag":"ventilation","Id":0},{"Pos":78,"Wall":0,"Tag":"canalization","Id":1},{"Pos":178,"Wall":0,"Tag":"window","Id":2},{"Pos":0,"Wall":0,"Tag":"entry","Id":3},{"Pos":-1,"Wall":-1,"Tag":"exit","Id":4}]},"output":[{"type":"W","subType":3,"wall":0,"width":120,"pos":0},{"type":"P","subType":0,"wall":0,"width":57,"pos":120},{"type":"C","subType":3,"wall":0,"width":120,"pos":177},{"type":"P","subType":0,"wall":0,"width":60,"pos":297},{"type":"S","subType":4,"wall":0,"width":120,"pos":357}]},{"input":{"walls":[489,489],"realWalls":[true,false],"utils":[{"Pos":241,"Wall":0,"Tag":"ventilation","Id":0},{"Pos":320,"Wall":0,"Tag":"canalization","Id":1},{"Pos":-1,"Wall":-1,"Tag":"window","Id":2},{"Pos":0,"Wall":0,"Tag":"entry","Id":3},{"Pos":-1,"Wall":-1,"Tag":"exit","Id":4}]},"output":[{"type":"S","subType":4,"wall":0,"width":120,"pos":0},{"type":"P","subType":0,"wall":0,"width":60,"pos":120},{"type":"C","subType":3,"wall":0,"width":120,"pos":180},{"type":"W","subType":3,"wall":0,"width":120,"pos":300},{"type":"P","subType":0,"wall":0,"width":69,"pos":420}]},{"input":{"walls":[172,172],"realWalls":[true,false],"utils":[{"Pos":1,"Wall":0,"Tag":"ventilation","Id":0},{"Pos":-1,"Wall":-1,"Tag":"canalization","Id":1},{"Pos":-1,"Wall":-1,"Tag":"window","Id":2},{"Pos":0,"Wall":0,"Tag":"entry","Id":3},{"Pos":-1,"Wall":-1,"Tag":"exit","Id":4}]},"output":[{"type":"C","subType":1,"wall":0,"width":60,"pos":0},{"type":"P","subType":0,"wall":0,"width":52,"pos":60},{"type":"W","subType":2,"wall":0,"width":60,"pos":112}]},{"input":{"walls":[170,170],"realWalls":[true,false],"utils":[{"Pos":31,"Wall":0,"Tag":"ventilation","Id":0},{"Pos":138,"Wall":0,"Tag":"canalization","Id":1},{"Pos":-1,"Wall":-1,"Tag":"window","Id":2},{"Pos":-1,"Wall":-1,"Tag":"entry","Id":3},{"Pos":-1,"Wall":-1,"Tag":"exit","Id":4}]},"output":[{"type":"C","subType":1,"wall":0,"width":60,"pos":0},{"type":"P","subType":0,"wall":0,"width":50,"pos":60},{"type":"W","subType":2,"wall":0,"width":60,"pos":110}]},{"input":{"walls":[529,529],"realWalls":[true,false],"utils":[{"Pos":353,"Wall":0,"Tag":"ventilation","Id":0},{"Pos":343,"Wall":0,"Tag":"canalization","Id":1},{"Pos":-1,"Wall":-1,"Tag":"window","Id":2},{"Pos":0,"Wall":0,"Tag":"entry","Id":3},{"Pos":-1,"Wall":-1,"Tag":"exit","Id":4}]},"output":[{"type":"S","subType":4,"wall":0,"width":120,"pos":0},{"type":"P","subType":0,"wall":0,"width":49,"pos":120},{"type":"P","subType":0,"wall":0,"width":60,"pos":169},{"type":"W","subType":3,"wall":0,"width":120,"pos":229},{"type":"C","subType":3,"wall":0,"width":120,"pos":349},{"type":"P","subType":0,"wall":0,"width":60,"pos":469}]},{"input":{"walls":[166,166],"realWalls":[true,false],"utils":[{"Pos":59,"Wall":0,"Tag":"ventilation","Id":0},{"Pos":-1,"Wall":-1,"Tag":"canalization","Id":1},{"Pos":7,"Wall":0,"Tag":"window","Id":2},{"Pos":0,"Wall":0,"Tag":"entry","Id":3},{"Pos":-1,"Wall":-1,"Tag":"exit","Id":4}]},"output":[{"type":"C","subType":1,"wall":0,"width":60,"pos":0},{"type":"P","subType":0,"wall":0,"width":46,"pos":60},{"type":"W","subType":2,"wall":0,"width":60,"pos":106}]},{"input":{"walls":[146,146],"realWalls":[true,false],"utils":[{"Pos":86,"Wall":0,"Tag":"ventilation","Id":0},{"Pos":88,"Wall":0,"Tag":"canalization","Id":1},{"Pos":108,"Wall":0,"Tag":"window","Id":2},{"Pos":0,"Wall":0,"Tag":"entry","Id":3},{"Pos":145,"Wall":0,"Tag":"exit","Id":4}]},"output":[{"type":"P","subType":0,"wall":0,"width":26,"pos":0},{"type":"C","subType":1,"wall":0,"width":60,"pos":26},{"type":"W","subType":2,"wall":0,"width":60,"pos":86}]},{"input":{"walls":[287,287],"realWalls":[true,false],"utils":[{"Pos":-1,"Wall":-1,"Tag":"ventilation","Id":0},{"Pos":-1,"Wall":-1,"Tag":"canalization","Id":1},{"Pos":-1,"Wall":-1,"Tag":"window","Id":2},{"Pos":0,"Wall":0,"Tag":"entry","Id":3},{"Pos":-1,"Wall":-1,"Tag":"exit","Id":4}]},"output":[{"type":"S","subType":2,"wall":0,"width":60,"pos":0},{"type":"P","subType":0,"wall":0,"width":47,"pos":60},{"type":"W","subType":2,"wall":0,"width":60,"pos":107},{"type":"P","subType":0,"wall":0,"width":60,"pos":167},{"type":"C","subType":2,"wall":0,"width":60,"pos":227}]},{"input":{"walls":[282,282],"realWalls":[true,false],"utils":[{"Pos":-1,"Wall":-1,"Tag":"ventilation","Id":0},{"Pos":77,"Wall":0,"Tag":"canalization","Id":1},{"Pos":-1,"Wall":-1,"Tag":"window","Id":2},{"Pos":-1,"Wall":-1,"Tag":"entry","Id":3},{"Pos":-1,"Wall":-1,"Tag":"exit","Id":4}]},"output":[{"type":"S","subType":2,"wall":0,"width":60,"pos":0},{"type":"W","subType":2,"wall":0,"width":60,"pos":60},{"type":"P","subType":0,"wall":0,"width":60,"pos":120},{"type":"P","subType":0,"wall":0,"width":42,"pos":180},{"type":"C","subType":2,"wall":0,"width":60,"pos":222}]},{"input":{"walls":[352,352],"realWalls":[true,false],"utils":[{"Pos":-1,"Wall":-1,"Tag":"ventilation","Id":0},{"Pos":283,"Wall":0,"Tag":"canalization","Id":1},{"Pos":-1,"Wall":-1,"Tag":"window","Id":2},{"Pos":0,"Wall":0,"Tag":"entry","Id":3},{"Pos":-1,"Wall":-1,"Tag":"exit","Id":4}]},"output":[{"type":"S","subType":3,"wall":0,"width":90,"pos":0},{"type":"C","subType":2,"wall":0,"width":60,"pos":90},{"type":"P","subType":0,"wall":0,"width":82,"pos":150},{"type":"W","subType":3,"wall":0,"width":120,"pos":232}]},{"input":{"walls":[489,489],"realWalls":[true,false],"utils":[{"Pos":416,"Wall":0,"Tag":"ventilation","Id":0},{"Pos":348,"Wall":0,"Tag":"canalization","Id":1},{"Pos":-1,"Wall":-1,"Tag":"window","Id":2},{"Pos":0,"Wall":0,"Tag":"entry","Id":3},{"Pos":487,"Wall":0,"Tag":"exit","Id":4}]},"output":[{"type":"S","subType":4,"wall":0,"width":120,"pos":0},{"type":"P","subType":0,"wall":0,"width":69,"pos":120},{"type":"P","subType":0,"wall":0,"width":60,"pos":189},{"type":"W","subType":3,"wall":0,"width":120,"pos":249},{"type":"C","subType":3,"wall":0,"width":120,"pos":369}]},{"input":{"walls":[218,218],"realWalls":[true,false],"utils":[{"Pos":-1,"Wall":-1,"Tag":"ventilation","Id":0},{"Pos":-1,"Wall":-1,"Tag":"canalization","Id":1},{"Pos":-1,"Wall":-1,"Tag":"window","Id":2},{"Pos":0,"Wall":0,"Tag":"entry","Id":3},{"Pos":-1,"Wall":-1,"Tag":"exit","Id":4}]},"output":[{"type":"S","subType":2,"wall":0,"width":60,"pos":0},{"type":"W","subType":2,"wall":0,"width":60,"pos":60},{"type":"P","subType":0,"wall":0,"width":38,"pos":120},{"type":"C","subType":2,"wall":0,"width":60,"pos":158}]},{"input":{"walls":[191,191],"realWalls":[true,false],"utils":[{"Pos":-1,"Wall":-1,"Tag":"ventilation","Id":0},{"Pos":123,"Wall":0,"Tag":"canalization","Id":1},{"Pos":-1,"Wall":-1,"Tag":"window","Id":2},{"Pos":0,"Wall":0,"Tag":"entry","Id":3},{"Pos":-1,"Wall":-1,"Tag":"exit","Id":4}]},"output":[{"type":"C","subType":2,"wall":0,"width":60,"pos":0},{"type":"P","subType":0,"wall":0,"width":11,"pos":60},{"type":"W","subType":2,"wall":0,"width":60,"pos":71},{"type":"S","subType":1,"wall":0,"width":60,"pos":131}]},{"input":{"walls":[254,254],"realWalls":[true,false],"utils":[{"Pos":-1,"Wall":-1,"Tag":"ventilation","Id":0},{"Pos":-1,"Wall":-1,"Tag":"canalization","Id":1},{"Pos":-1,"Wall":-1,"Tag":"window","Id":2},{"Pos":0,"Wall":0,"Tag":"entry","Id":3},{"Pos":253,"Wall":0,"Tag":"exit","Id":4}]},"output":[{"type":"S","subType":2,"wall":0,"width":60,"pos":0},{"type":"W","subType":2,"wall":0,"width":60,"pos":60},{"type":"P","subType":0,"wall":0,"width":74,"pos":120},{"type":"C","subType":2,"wall":0,"width":60,"pos":194}]},{"input":{"walls":[481,481],"realWalls":[true,false],"utils":[{"Pos":271,"Wall":0,"Tag":"ventilation","Id":0},{"Pos":-1,"Wall":-1,"Tag":"canalization","Id":1},{"Pos":-1,"Wall":-1,"Tag":"window","Id":2},{"Pos":0,"Wall":0,"Tag":"entry","Id":3},{"Pos":-1,"Wall":-1,"Tag":"exit","Id":4}]},"output":[{"type":"S","subType":4,"wall":0,"width":120,"pos":0},{"type":"P","subType":0,"wall":0,"width":60,"pos":120},{"type":"C","subType":3,"wall":0,"width":120,"pos":180},{"type":"P","subType":0,"wall":0,"width":61,"pos":300},{"type":"W","subType":3,"wall":0,"width":120,"pos":361}]},{"input":{"walls":[185,185],"realWalls":[true,false],"utils":[{"Pos":46,"Wall":0,"Tag":"ventilation","Id":0},{"Pos":72,"Wall":0,"Tag":"canalization","Id":1},{"Pos":-1,"Wall":-1,"Tag":"window","Id":2},{"Pos":0,"Wall":0,"Tag":"entry","Id":3},{"Pos":184,"Wall":0,"Tag":"exit","Id":4}]},"output":[{"type":"C","subType":2,"wall":0,"width":60,"pos":0},{"type":"P","subType":0,"wall":0,"width":5,"pos":60},{"type":"W","subType":2,"wall":0,"width":60,"pos":65},{"type":"S","subType":1,"wall":0,"width":60,"pos":125}]},{"input":{"walls":[434,434],"realWalls":[true,false],"utils":[{"Pos":360,"Wall":0,"Tag":"ventilation","Id":0},{"Pos":211,"Wall":0,"Tag":"canalization","Id":1},{"Pos":-1,"Wall":-1,"Tag":"window","Id":2},{"Pos":-1,"Wall":-1,"Tag":"entry","Id":3},{"Pos":433,"Wall":0,"Tag":"exit","Id":4}]},"output":[{"type":"S","subType":3,"wall":0,"width":90,"pos":0},{"type":"P","subType":0,"wall":0,"width":44,"pos":90},{"type":"W","subType":3,"wall":0,"width":120,"pos":134},{"type":"P","subType":0,"wall":0,"width":60,"pos":254},{"type":"C","subType":3,"wall":0,"width":120,"pos":314}]},{"input":{"walls":[203,203],"realWalls":[true,false],"utils":[{"Pos":83,"Wall":0,"Tag":"ventilation","Id":0},{"Pos":-1,"Wall":-1,"Tag":"canalization","Id":1},{"Pos":-1,"Wall":-1,"Tag":"window","Id":2},{"Pos":0,"Wall":0,"Tag":"entry","Id":3},{"Pos":-1,"Wall":-1,"Tag":"exit","Id":4}]},"output":[{"type":"S","subType":1,"wall":0,"width":60,"pos":0},{"type":"C","subType":2,"wall":0,"width":60,"pos":60},{"type":"P","subType":0,"wall":0,"width":23,"pos":120},{"type":"W","subType":2,"wall":0,"width":60,"pos":143}]},{"input":{"walls":[594,594],"realWalls":[true,false],"utils":[{"Pos":173,"Wall":0,"Tag":"ventilation","Id":0},{"Pos":418,"Wall":0,"Tag":"canalization","Id":1},{"Pos":-1,"Wall":-1,"Tag":"window","Id":2},{"Pos":-1,"Wall":-1,"Tag":"entry","Id":3},{"Pos":-1,"Wall":-1,"Tag":"exit","Id":4}]},"output":[{"type":"P","subType":0,"wall":0,"width":60,"pos":0},{"type":"P","subType":0,"wall":0,"width":54,"pos":60},{"type":"C","subType":3,"wall":0,"width":120,"pos":114},{"type":"P","subType":0,"wall":0,"width":60,"pos":234},{"type":"P","subType":0,"wall":0,"width":60,"pos":294},{"type":"W","subType":3,"wall":0,"width":120,"pos":354},{"type":"S","subType":4,"wall":0,"width":120,"pos":474}]},{"input":{"walls":[594,594],"realWalls":[true,false],"utils":[{"Pos":173,"Wall":0,"Tag":"ventilation","Id":0},{"Pos":418,"Wall":0,"Tag":"canalization","Id":1},{"Pos":-1,"Wall":-1,"Tag":"window","Id":2},{"Pos":-1,"Wall":-1,"Tag":"entry","Id":3},{"Pos":-1,"Wall":-1,"Tag":"exit","Id":4}]},"output":[{"type":"P","subType":0,"wall":0,"width":54,"pos":0},{"type":"P","subType":0,"wall":0,"width":60,"pos":54},{"type":"C","subType":3,"wall":0,"width":120,"pos":114},{"type":"P","subType":0,"wall":0,"width":60,"pos":234},{"type":"P","subType":0,"wall":0,"width":60,"pos":294},{"type":"W","subType":3,"wall":0,"width":120,"pos":354},{"type":"S","subType":4,"wall":0,"width":120,"pos":474}]},{"input":{"walls":[545,545],"realWalls":[true,false],"utils":[{"Pos":237,"Wall":0,"Tag":"ventilation","Id":0},{"Pos":400,"Wall":0,"Tag":"canalization","Id":1},{"Pos":505,"Wall":0,"Tag":"window","Id":2},{"Pos":0,"Wall":0,"Tag":"entry","Id":3},{"Pos":-1,"Wall":-1,"Tag":"exit","Id":4}]},"output":[{"type":"S","subType":4,"wall":0,"width":120,"pos":0},{"type":"P","subType":0,"wall":0,"width":65,"pos":120},{"type":"C","subType":3,"wall":0,"width":120,"pos":185},{"type":"P","subType":0,"wall":0,"width":60,"pos":305},{"type":"W","subType":3,"wall":0,"width":120,"pos":365},{"type":"P","subType":0,"wall":0,"width":60,"pos":485}]},{"input":{"walls":[545,545],"realWalls":[true,false],"utils":[{"Pos":236,"Wall":0,"Tag":"ventilation","Id":0},{"Pos":400,"Wall":0,"Tag":"canalization","Id":1},{"Pos":505,"Wall":0,"Tag":"window","Id":2},{"Pos":0,"Wall":0,"Tag":"entry","Id":3},{"Pos":-1,"Wall":-1,"Tag":"exit","Id":4}]},"output":[{"type":"S","subType":4,"wall":0,"width":120,"pos":0},{"type":"P","subType":0,"wall":0,"width":60,"pos":120},{"type":"C","subType":3,"wall":0,"width":120,"pos":180},{"type":"P","subType":0,"wall":0,"width":60,"pos":300},{"type":"W","subType":3,"wall":0,"width":120,"pos":360},{"type":"P","subType":0,"wall":0,"width":65,"pos":480}]},{"input":{"walls":[150,150],"realWalls":[true,false],"utils":[{"Pos":67,"Wall":0,"Tag":"ventilation","Id":0},{"Pos":111,"Wall":0,"Tag":"canalization","Id":1},{"Pos":3,"Wall":0,"Tag":"window","Id":2},{"Pos":0,"Wall":0,"Tag":"entry","Id":3},{"Pos":-1,"Wall":-1,"Tag":"exit","Id":4}]},"output":[{"type":"P","subType":0,"wall":0,"width":30,"pos":0},{"type":"C","subType":1,"wall":0,"width":60,"pos":30},{"type":"W","subType":2,"wall":0,"width":60,"pos":90}]},{"input":{"walls":[226,226],"realWalls":[true,false],"utils":[{"Pos":147,"Wall":0,"Tag":"ventilation","Id":0},{"Pos":-1,"Wall":-1,"Tag":"canalization","Id":1},{"Pos":-1,"Wall":-1,"Tag":"window","Id":2},{"Pos":0,"Wall":0,"Tag":"entry","Id":3},{"Pos":-1,"Wall":-1,"Tag":"exit","Id":4}]},"output":[{"type":"W","subType":2,"wall":0,"width":60,"pos":0},{"type":"P","subType":0,"wall":0,"width":46,"pos":60},{"type":"C","subType":2,"wall":0,"width":60,"pos":106},{"type":"S","subType":2,"wall":0,"width":60,"pos":166}]},{"input":{"walls":[530,530],"realWalls":[true,false],"utils":[{"Pos":448,"Wall":0,"Tag":"ventilation","Id":0},{"Pos":253,"Wall":0,"Tag":"canalization","Id":1},{"Pos":-1,"Wall":-1,"Tag":"window","Id":2},{"Pos":0,"Wall":0,"Tag":"entry","Id":3},{"Pos":-1,"Wall":-1,"Tag":"exit","Id":4}]},"output":[{"type":"S","subType":4,"wall":0,"width":120,"pos":0},{"type":"P","subType":0,"wall":0,"width":60,"pos":120},{"type":"W","subType":3,"wall":0,"width":120,"pos":180},{"type":"P","subType":0,"wall":0,"width":50,"pos":300},{"type":"P","subType":0,"wall":0,"width":60,"pos":350},{"type":"C","subType":3,"wall":0,"width":120,"pos":410}]},{"input":{"walls":[515,515],"realWalls":[true,false],"utils":[{"Pos":219,"Wall":0,"Tag":"ventilation","Id":0},{"Pos":260,"Wall":0,"Tag":"canalization","Id":1},{"Pos":-1,"Wall":-1,"Tag":"window","Id":2},{"Pos":0,"Wall":0,"Tag":"entry","Id":3},{"Pos":515,"Wall":0,"Tag":"exit","Id":4}]},"output":[{"type":"P","subType":0,"wall":0,"width":60,"pos":0},{"type":"P","subType":0,"wall":0,"width":60,"pos":60},{"type":"C","subType":3,"wall":0,"width":120,"pos":120},{"type":"W","subType":3,"wall":0,"width":120,"pos":240},{"type":"P","subType":0,"wall":0,"width":35,"pos":360},{"type":"S","subType":4,"wall":0,"width":120,"pos":395}]},{"input":{"walls":[585,585],"realWalls":[true,false],"utils":[{"Pos":244,"Wall":0,"Tag":"ventilation","Id":0},{"Pos":431,"Wall":0,"Tag":"canalization","Id":1},{"Pos":-1,"Wall":-1,"Tag":"window","Id":2},{"Pos":0,"Wall":0,"Tag":"entry","Id":3},{"Pos":585,"Wall":0,"Tag":"exit","Id":4}]},"output":[{"type":"S","subType":4,"wall":0,"width":120,"pos":0},{"type":"P","subType":0,"wall":0,"width":60,"pos":120},{"type":"C","subType":3,"wall":0,"width":120,"pos":180},{"type":"P","subType":0,"wall":0,"width":60,"pos":300},{"type":"P","subType":0,"wall":0,"width":60,"pos":360},{"type":"W","subType":3,"wall":0,"width":120,"pos":420},{"type":"P","subType":0,"wall":0,"width":45,"pos":540}]},{"input":{"walls":[558,558],"realWalls":[true,false],"utils":[{"Pos":-1,"Wall":-1,"Tag":"ventilation","Id":0},{"Pos":277,"Wall":0,"Tag":"canalization","Id":1},{"Pos":-1,"Wall":-1,"Tag":"window","Id":2},{"Pos":0,"Wall":0,"Tag":"entry","Id":3},{"Pos":-1,"Wall":-1,"Tag":"exit","Id":4}]},"output":[{"type":"S","subType":4,"wall":0,"width":120,"pos":0},{"type":"P","subType":0,"wall":0,"width":78,"pos":120},{"type":"W","subType":3,"wall":0,"width":120,"pos":198},{"type":"P","subType":0,"wall":0,"width":60,"pos":318},{"type":"P","subType":0,"wall":0,"width":60,"pos":378},{"type":"C","subType":3,"wall":0,"width":120,"pos":438}]},{"input":{"walls":[155,155],"realWalls":[true,false],"utils":[{"Pos":100,"Wall":0,"Tag":"ventilation","Id":0},{"Pos":73,"Wall":0,"Tag":"canalization","Id":1},{"Pos":25,"Wall":0,"Tag":"window","Id":2},{"Pos":0,"Wall":0,"Tag":"entry","Id":3},{"Pos":-1,"Wall":-1,"Tag":"exit","Id":4}]},"output":[{"type":"P","subType":0,"wall":0,"width":35,"pos":0},{"type":"W","subType":2,"wall":0,"width":60,"pos":35},{"type":"C","subType":1,"wall":0,"width":60,"pos":95}]},{"input":{"walls":[542,542],"realWalls":[true,false],"utils":[{"Pos":305,"Wall":0,"Tag":"ventilation","Id":0},{"Pos":235,"Wall":0,"Tag":"canalization","Id":1},{"Pos":-1,"Wall":-1,"Tag":"window","Id":2},{"Pos":0,"Wall":0,"Tag":"entry","Id":3},{"Pos":-1,"Wall":-1,"Tag":"exit","Id":4}]},"output":[{"type":"S","subType":4,"wall":0,"width":120,"pos":0},{"type":"W","subType":3,"wall":0,"width":120,"pos":120},{"type":"P","subType":0,"wall":0,"width":62,"pos":240},{"type":"C","subType":3,"wall":0,"width":120,"pos":302},{"type":"P","subType":0,"wall":0,"width":60,"pos":422},{"type":"P","subType":0,"wall":0,"width":60,"pos":482}]},{"input":{"walls":[231,231],"realWalls":[true,false],"utils":[{"Pos":34,"Wall":0,"Tag":"ventilation","Id":0},{"Pos":132,"Wall":0,"Tag":"canalization","Id":1},{"Pos":35,"Wall":0,"Tag":"window","Id":2},{"Pos":0,"Wall":0,"Tag":"entry","Id":3},{"Pos":-1,"Wall":-1,"Tag":"exit","Id":4}]},"output":[{"type":"C","subType":2,"wall":0,"width":60,"pos":0},{"type":"P","subType":0,"wall":0,"width":51,"pos":60},{"type":"W","subType":2,"wall":0,"width":60,"pos":111},{"type":"S","subType":2,"wall":0,"width":60,"pos":171}]},{"input":{"walls":[105,105],"realWalls":[true,false],"utils":[{"Pos":18,"Wall":0,"Tag":"ventilation","Id":0},{"Pos":11,"Wall":0,"Tag":"canalization","Id":1},{"Pos":20,"Wall":0,"Tag":"window","Id":2},{"Pos":0,"Wall":0,"Tag":"entry","Id":3},{"Pos":105,"Wall":0,"Tag":"exit","Id":4}]},"output":[{"type":"W","subType":1,"wall":0,"width":30,"pos":0},{"type":"C","subType":1,"wall":0,"width":60,"pos":30},{"type":"P","subType":0,"wall":0,"width":15,"pos":90}]},{"input":{"walls":[229,229],"realWalls":[true,false],"utils":[{"Pos":218,"Wall":0,"Tag":"ventilation","Id":0},{"Pos":28,"Wall":0,"Tag":"canalization","Id":1},{"Pos":-1,"Wall":-1,"Tag":"window","Id":2},{"Pos":0,"Wall":0,"Tag":"entry","Id":3},{"Pos":228,"Wall":0,"Tag":"exit","Id":4}]},"output":[{"type":"W","subType":2,"wall":0,"width":60,"pos":0},{"type":"S","subType":2,"wall":0,"width":60,"pos":60},{"type":"P","subType":0,"wall":0,"width":49,"pos":120},{"type":"C","subType":2,"wall":0,"width":60,"pos":169}]},{"input":{"walls":[505,505],"realWalls":[true,false],"utils":[{"Pos":155,"Wall":0,"Tag":"ventilation","Id":0},{"Pos":98,"Wall":0,"Tag":"canalization","Id":1},{"Pos":-1,"Wall":-1,"Tag":"window","Id":2},{"Pos":0,"Wall":0,"Tag":"entry","Id":3},{"Pos":503,"Wall":0,"Tag":"exit","Id":4}]},"output":[{"type":"W","subType":3,"wall":0,"width":120,"pos":0},{"type":"C","subType":3,"wall":0,"width":120,"pos":120},{"type":"P","subType":0,"wall":0,"width":60,"pos":240},{"type":"P","subType":0,"wall":0,"width":85,"pos":300},{"type":"S","subType":4,"wall":0,"width":120,"pos":385}]},{"input":{"walls":[94,94],"realWalls":[true,false],"utils":[{"Pos":43,"Wall":0,"Tag":"ventilation","Id":0},{"Pos":-1,"Wall":-1,"Tag":"canalization","Id":1},{"Pos":-1,"Wall":-1,"Tag":"window","Id":2},{"Pos":-1,"Wall":-1,"Tag":"entry","Id":3},{"Pos":-1,"Wall":-1,"Tag":"exit","Id":4}]},"output":[{"type":"W","subType":1,"wall":0,"width":30,"pos":0},{"type":"P","subType":0,"wall":0,"width":4,"pos":30},{"type":"C","subType":1,"wall":0,"width":60,"pos":34}]},{"input":{"walls":[483,483],"realWalls":[true,false],"utils":[{"Pos":-1,"Wall":-1,"Tag":"ventilation","Id":0},{"Pos":218,"Wall":0,"Tag":"canalization","Id":1},{"Pos":213,"Wall":0,"Tag":"window","Id":2},{"Pos":0,"Wall":0,"Tag":"entry","Id":3},{"Pos":-1,"Wall":-1,"Tag":"exit","Id":4}]},"output":[{"type":"P","subType":0,"wall":0,"width":63,"pos":0},{"type":"C","subType":3,"wall":0,"width":120,"pos":63},{"type":"W","subType":3,"wall":0,"width":120,"pos":183},{"type":"P","subType":0,"wall":0,"width":60,"pos":303},{"type":"S","subType":4,"wall":0,"width":120,"pos":363}]},{"input":{"walls":[251,251],"realWalls":[true,false],"utils":[{"Pos":-1,"Wall":-1,"Tag":"ventilation","Id":0},{"Pos":6,"Wall":0,"Tag":"canalization","Id":1},{"Pos":148,"Wall":0,"Tag":"window","Id":2},{"Pos":0,"Wall":0,"Tag":"entry","Id":3},{"Pos":-1,"Wall":-1,"Tag":"exit","Id":4}]},"output":[{"type":"W","subType":2,"wall":0,"width":60,"pos":0},{"type":"P","subType":0,"wall":0,"width":71,"pos":60},{"type":"C","subType":2,"wall":0,"width":60,"pos":131},{"type":"S","subType":2,"wall":0,"width":60,"pos":191}]},{"input":{"walls":[173,173],"realWalls":[true,false],"utils":[{"Pos":-1,"Wall":-1,"Tag":"ventilation","Id":0},{"Pos":150,"Wall":0,"Tag":"canalization","Id":1},{"Pos":-1,"Wall":-1,"Tag":"window","Id":2},{"Pos":0,"Wall":0,"Tag":"entry","Id":3},{"Pos":-1,"Wall":-1,"Tag":"exit","Id":4}]},"output":[{"type":"C","subType":1,"wall":0,"width":60,"pos":0},{"type":"P","subType":0,"wall":0,"width":53,"pos":60},{"type":"W","subType":2,"wall":0,"width":60,"pos":113}]},{"input":{"walls":[466,466],"realWalls":[true,false],"utils":[{"Pos":173,"Wall":0,"Tag":"ventilation","Id":0},{"Pos":182,"Wall":0,"Tag":"canalization","Id":1},{"Pos":-1,"Wall":-1,"Tag":"window","Id":2},{"Pos":0,"Wall":0,"Tag":"entry","Id":3},{"Pos":466,"Wall":0,"Tag":"exit","Id":4}]},"output":[{"type":"P","subType":0,"wall":0,"width":60,"pos":0},{"type":"C","subType":3,"wall":0,"width":120,"pos":60},{"type":"W","subType":3,"wall":0,"width":120,"pos":180},{"type":"P","subType":0,"wall":0,"width":46,"pos":300},{"type":"S","subType":4,"wall":0,"width":120,"pos":346}]},{"input":{"walls":[263,263],"realWalls":[true,false],"utils":[{"Pos":159,"Wall":0,"Tag":"ventilation","Id":0},{"Pos":-1,"Wall":-1,"Tag":"canalization","Id":1},{"Pos":-1,"Wall":-1,"Tag":"window","Id":2},{"Pos":0,"Wall":0,"Tag":"entry","Id":3},{"Pos":-1,"Wall":-1,"Tag":"exit","Id":4}]},"output":[{"type":"W","subType":2,"wall":0,"width":60,"pos":0},{"type":"P","subType":0,"wall":0,"width":83,"pos":60},{"type":"C","subType":2,"wall":0,"width":60,"pos":143},{"type":"S","subType":2,"wall":0,"width":60,"pos":203}]},{"input":{"walls":[93,93],"realWalls":[true,false],"utils":[{"Pos":3,"Wall":0,"Tag":"ventilation","Id":0},{"Pos":35,"Wall":0,"Tag":"canalization","Id":1},{"Pos":31,"Wall":0,"Tag":"window","Id":2},{"Pos":0,"Wall":0,"Tag":"entry","Id":3},{"Pos":-1,"Wall":-1,"Tag":"exit","Id":4}]},"output":[{"type":"C","subType":1,"wall":0,"width":60,"pos":0},{"type":"W","subType":1,"wall":0,"width":30,"pos":60},{"type":"P","subType":0,"wall":0,"width":3,"pos":90}]},{"input":{"walls":[279,279],"realWalls":[true,false],"utils":[{"Pos":35,"Wall":0,"Tag":"ventilation","Id":0},{"Pos":-1,"Wall":-1,"Tag":"canalization","Id":1},{"Pos":-1,"Wall":-1,"Tag":"window","Id":2},{"Pos":0,"Wall":0,"Tag":"entry","Id":3},{"Pos":-1,"Wall":-1,"Tag":"exit","Id":4}]},"output":[{"type":"C","subType":2,"wall":0,"width":60,"pos":0},{"type":"P","subType":0,"wall":0,"width":60,"pos":60},{"type":"W","subType":2,"wall":0,"width":60,"pos":120},{"type":"P","subType":0,"wall":0,"width":39,"pos":180},{"type":"S","subType":2,"wall":0,"width":60,"pos":219}]},{"input":{"walls":[161,161],"realWalls":[true,false],"utils":[{"Pos":43,"Wall":0,"Tag":"ventilation","Id":0},{"Pos":151,"Wall":0,"Tag":"canalization","Id":1},{"Pos":-1,"Wall":-1,"Tag":"window","Id":2},{"Pos":0,"Wall":0,"Tag":"entry","Id":3},{"Pos":-1,"Wall":-1,"Tag":"exit","Id":4}]},"output":[{"type":"C","subType":1,"wall":0,"width":60,"pos":0},{"type":"P","subType":0,"wall":0,"width":41,"pos":60},{"type":"W","subType":2,"wall":0,"width":60,"pos":101}]},{"input":{"walls":[451,451],"realWalls":[true,false],"utils":[{"Pos":213,"Wall":0,"Tag":"ventilation","Id":0},{"Pos":373,"Wall":0,"Tag":"canalization","Id":1},{"Pos":-1,"Wall":-1,"Tag":"window","Id":2},{"Pos":0,"Wall":0,"Tag":"entry","Id":3},{"Pos":451,"Wall":0,"Tag":"exit","Id":4}]},"output":[{"type":"S","subType":4,"wall":0,"width":120,"pos":0},{"type":"P","subType":0,"wall":0,"width":31,"pos":120},{"type":"C","subType":3,"wall":0,"width":120,"pos":151},{"type":"P","subType":0,"wall":0,"width":60,"pos":271},{"type":"W","subType":3,"wall":0,"width":120,"pos":331}]},{"input":{"walls":[520,520],"realWalls":[true,false],"utils":[{"Pos":164,"Wall":0,"Tag":"ventilation","Id":0},{"Pos":30,"Wall":0,"Tag":"canalization","Id":1},{"Pos":320,"Wall":0,"Tag":"window","Id":2},{"Pos":0,"Wall":0,"Tag":"entry","Id":3},{"Pos":-1,"Wall":-1,"Tag":"exit","Id":4}]},"output":[{"type":"W","subType":3,"wall":0,"width":120,"pos":0},{"type":"P","subType":0,"wall":0,"width":40,"pos":120},{"type":"C","subType":3,"wall":0,"width":120,"pos":160},{"type":"P","subType":0,"wall":0,"width":60,"pos":280},{"type":"P","subType":0,"wall":0,"width":60,"pos":340},{"type":"S","subType":4,"wall":0,"width":120,"pos":400}]},{"input":{"walls":[564,564],"realWalls":[true,false],"utils":[{"Pos":333,"Wall":0,"Tag":"ventilation","Id":0},{"Pos":343,"Wall":0,"Tag":"canalization","Id":1},{"Pos":-1,"Wall":-1,"Tag":"window","Id":2},{"Pos":0,"Wall":0,"Tag":"entry","Id":3},{"Pos":-1,"Wall":-1,"Tag":"exit","Id":4}]},"output":[{"type":"S","subType":4,"wall":0,"width":120,"pos":0},{"type":"P","subType":0,"wall":0,"width":84,"pos":120},{"type":"C","subType":3,"wall":0,"width":120,"pos":204},{"type":"W","subType":3,"wall":0,"width":120,"pos":324},{"type":"P","subType":0,"wall":0,"width":60,"pos":444},{"type":"P","subType":0,"wall":0,"width":60,"pos":504}]},{"input":{"walls":[465,465],"realWalls":[true,false],"utils":[{"Pos":113,"Wall":0,"Tag":"ventilation","Id":0},{"Pos":150,"Wall":0,"Tag":"canalization","Id":1},{"Pos":-1,"Wall":-1,"Tag":"window","Id":2},{"Pos":0,"Wall":0,"Tag":"entry","Id":3},{"Pos":-1,"Wall":-1,"Tag":"exit","Id":4}]},"output":[{"type":"C","subType":3,"wall":0,"width":120,"pos":0},{"type":"W","subType":3,"wall":0,"width":120,"pos":120},{"type":"P","subType":0,"wall":0,"width":45,"pos":240},{"type":"P","subType":0,"wall":0,"width":60,"pos":285},{"type":"S","subType":4,"wall":0,"width":120,"pos":345}]},{"input":{"walls":[408,408],"realWalls":[true,false],"utils":[{"Pos":148,"Wall":0,"Tag":"ventilation","Id":0},{"Pos":298,"Wall":0,"Tag":"canalization","Id":1},{"Pos":-1,"Wall":-1,"Tag":"window","Id":2},{"Pos":0,"Wall":0,"Tag":"entry","Id":3},{"Pos":-1,"Wall":-1,"Tag":"exit","Id":4}]},"output":[{"type":"S","subType":3,"wall":0,"width":90,"pos":0},{"type":"P","subType":0,"wall":0,"width":60,"pos":90},{"type":"C","subType":2,"wall":0,"width":60,"pos":150},{"type":"P","subType":0,"wall":0,"width":78,"pos":210},{"type":"W","subType":3,"wall":0,"width":120,"pos":288}]},{"input":{"walls":[263,263],"realWalls":[true,false],"utils":[{"Pos":146,"Wall":0,"Tag":"ventilation","Id":0},{"Pos":-1,"Wall":-1,"Tag":"canalization","Id":1},{"Pos":-1,"Wall":-1,"Tag":"window","Id":2},{"Pos":0,"Wall":0,"Tag":"entry","Id":3},{"Pos":-1,"Wall":-1,"Tag":"exit","Id":4}]},"output":[{"type":"W","subType":2,"wall":0,"width":60,"pos":0},{"type":"P","subType":0,"wall":0,"width":83,"pos":60},{"type":"C","subType":2,"wall":0,"width":60,"pos":143},{"type":"S","subType":2,"wall":0,"width":60,"pos":203}]},{"input":{"walls":[494,494],"realWalls":[true,false],"utils":[{"Pos":-1,"Wall":-1,"Tag":"ventilation","Id":0},{"Pos":-1,"Wall":-1,"Tag":"canalization","Id":1},{"Pos":317,"Wall":0,"Tag":"window","Id":2},{"Pos":0,"Wall":0,"Tag":"entry","Id":3},{"Pos":-1,"Wall":-1,"Tag":"exit","Id":4}]},"output":[{"type":"S","subType":4,"wall":0,"width":120,"pos":0},{"type":"W","subType":3,"wall":0,"width":120,"pos":120},{"type":"P","subType":0,"wall":0,"width":60,"pos":240},{"type":"C","subType":3,"wall":0,"width":120,"pos":300},{"type":"P","subType":0,"wall":0,"width":74,"pos":420}]},{"input":{"walls":[190,190],"realWalls":[true,false],"utils":[{"Pos":160,"Wall":0,"Tag":"ventilation","Id":0},{"Pos":166,"Wall":0,"Tag":"canalization","Id":1},{"Pos":-1,"Wall":-1,"Tag":"window","Id":2},{"Pos":0,"Wall":0,"Tag":"entry","Id":3},{"Pos":-1,"Wall":-1,"Tag":"exit","Id":4}]},"output":[{"type":"S","subType":1,"wall":0,"width":60,"pos":0},{"type":"P","subType":0,"wall":0,"width":10,"pos":60},{"type":"C","subType":2,"wall":0,"width":60,"pos":70},{"type":"W","subType":2,"wall":0,"width":60,"pos":130}]},{"input":{"walls":[146,146],"realWalls":[true,false],"utils":[{"Pos":81,"Wall":0,"Tag":"ventilation","Id":0},{"Pos":128,"Wall":0,"Tag":"canalization","Id":1},{"Pos":-1,"Wall":-1,"Tag":"window","Id":2},{"Pos":0,"Wall":0,"Tag":"entry","Id":3},{"Pos":145,"Wall":0,"Tag":"exit","Id":4}]},"output":[{"type":"P","subType":0,"wall":0,"width":26,"pos":0},{"type":"C","subType":1,"wall":0,"width":60,"pos":26},{"type":"W","subType":2,"wall":0,"width":60,"pos":86}]},{"input":{"walls":[284,284],"realWalls":[true,false],"utils":[{"Pos":253,"Wall":0,"Tag":"ventilation","Id":0},{"Pos":-1,"Wall":-1,"Tag":"canalization","Id":1},{"Pos":-1,"Wall":-1,"Tag":"window","Id":2},{"Pos":0,"Wall":0,"Tag":"entry","Id":3},{"Pos":283,"Wall":0,"Tag":"exit","Id":4}]},"output":[{"type":"S","subType":2,"wall":0,"width":60,"pos":0},{"type":"P","subType":0,"wall":0,"width":44,"pos":60},{"type":"W","subType":2,"wall":0,"width":60,"pos":104},{"type":"P","subType":0,"wall":0,"width":60,"pos":164},{"type":"C","subType":2,"wall":0,"width":60,"pos":224}]},{"input":{"walls":[133,133],"realWalls":[true,false],"utils":[{"Pos":-1,"Wall":-1,"Tag":"ventilation","Id":0},{"Pos":24,"Wall":0,"Tag":"canalization","Id":1},{"Pos":-1,"Wall":-1,"Tag":"window","Id":2},{"Pos":0,"Wall":0,"Tag":"entry","Id":3},{"Pos":-1,"Wall":-1,"Tag":"exit","Id":4}]},"output":[{"type":"W","subType":2,"wall":0,"width":60,"pos":0},{"type":"P","subType":0,"wall":0,"width":13,"pos":60},{"type":"C","subType":1,"wall":0,"width":60,"pos":73}]},{"input":{"walls":[417,417],"realWalls":[true,false],"utils":[{"Pos":-1,"Wall":-1,"Tag":"ventilation","Id":0},{"Pos":-1,"Wall":-1,"Tag":"canalization","Id":1},{"Pos":-1,"Wall":-1,"Tag":"window","Id":2},{"Pos":0,"Wall":0,"Tag":"entry","Id":3},{"Pos":-1,"Wall":-1,"Tag":"exit","Id":4}]},"output":[{"type":"S","subType":3,"wall":0,"width":90,"pos":0},{"type":"P","subType":0,"wall":0,"width":60,"pos":90},{"type":"W","subType":3,"wall":0,"width":120,"pos":150},{"type":"P","subType":0,"wall":0,"width":87,"pos":270},{"type":"C","subType":2,"wall":0,"width":60,"pos":357}]},{"input":{"walls":[459,459],"realWalls":[true,false],"utils":[{"Pos":135,"Wall":0,"Tag":"ventilation","Id":0},{"Pos":26,"Wall":0,"Tag":"canalization","Id":1},{"Pos":-1,"Wall":-1,"Tag":"window","Id":2},{"Pos":0,"Wall":0,"Tag":"entry","Id":3},{"Pos":457,"Wall":0,"Tag":"exit","Id":4}]},"output":[{"type":"W","subType":3,"wall":0,"width":120,"pos":0},{"type":"C","subType":3,"wall":0,"width":120,"pos":120},{"type":"P","subType":0,"wall":0,"width":60,"pos":240},{"type":"P","subType":0,"wall":0,"width":39,"pos":300},{"type":"S","subType":4,"wall":0,"width":120,"pos":339}]},{"input":{"walls":[428,428],"realWalls":[true,false],"utils":[{"Pos":220,"Wall":0,"Tag":"ventilation","Id":0},{"Pos":363,"Wall":0,"Tag":"canalization","Id":1},{"Pos":-1,"Wall":-1,"Tag":"window","Id":2},{"Pos":0,"Wall":0,"Tag":"entry","Id":3},{"Pos":427,"Wall":0,"Tag":"exit","Id":4}]},"output":[{"type":"S","subType":3,"wall":0,"width":90,"pos":0},{"type":"P","subType":0,"wall":0,"width":60,"pos":90},{"type":"C","subType":3,"wall":0,"width":120,"pos":150},{"type":"P","subType":0,"wall":0,"width":38,"pos":270},{"type":"W","subType":3,"wall":0,"width":120,"pos":308}]},{"input":{"walls":[315,315],"realWalls":[true,false],"utils":[{"Pos":144,"Wall":0,"Tag":"ventilation","Id":0},{"Pos":278,"Wall":0,"Tag":"canalization","Id":1},{"Pos":273,"Wall":0,"Tag":"window","Id":2},{"Pos":0,"Wall":0,"Tag":"entry","Id":3},{"Pos":-1,"Wall":-1,"Tag":"exit","Id":4}]},"output":[{"type":"S","subType":3,"wall":0,"width":90,"pos":0},{"type":"C","subType":2,"wall":0,"width":60,"pos":90},{"type":"P","subType":0,"wall":0,"width":45,"pos":150},{"type":"W","subType":3,"wall":0,"width":120,"pos":195}]},{"input":{"walls":[152,152],"realWalls":[true,false],"utils":[{"Pos":71,"Wall":0,"Tag":"ventilation","Id":0},{"Pos":-1,"Wall":-1,"Tag":"canalization","Id":1},{"Pos":-1,"Wall":-1,"Tag":"window","Id":2},{"Pos":0,"Wall":0,"Tag":"entry","Id":3},{"Pos":-1,"Wall":-1,"Tag":"exit","Id":4}]},"output":[{"type":"P","subType":0,"wall":0,"width":32,"pos":0},{"type":"C","subType":1,"wall":0,"width":60,"pos":32},{"type":"W","subType":2,"wall":0,"width":60,"pos":92}]},{"input":{"walls":[234,234],"realWalls":[true,false],"utils":[{"Pos":-1,"Wall":-1,"Tag":"ventilation","Id":0},{"Pos":52,"Wall":0,"Tag":"canalization","Id":1},{"Pos":-1,"Wall":-1,"Tag":"window","Id":2},{"Pos":0,"Wall":0,"Tag":"entry","Id":3},{"Pos":-1,"Wall":-1,"Tag":"exit","Id":4}]},"output":[{"type":"W","subType":2,"wall":0,"width":60,"pos":0},{"type":"P","subType":0,"wall":0,"width":54,"pos":60},{"type":"C","subType":2,"wall":0,"width":60,"pos":114},{"type":"S","subType":2,"wall":0,"width":60,"pos":174}]},{"input":{"walls":[156,156],"realWalls":[true,false],"utils":[{"Pos":86,"Wall":0,"Tag":"ventilation","Id":0},{"Pos":-1,"Wall":-1,"Tag":"canalization","Id":1},{"Pos":-1,"Wall":-1,"Tag":"window","Id":2},{"Pos":0,"Wall":0,"Tag":"entry","Id":3},{"Pos":-1,"Wall":-1,"Tag":"exit","Id":4}]},"output":[{"type":"W","subType":2,"wall":0,"width":60,"pos":0},{"type":"C","subType":1,"wall":0,"width":60,"pos":60},{"type":"P","subType":0,"wall":0,"width":36,"pos":120}]},{"input":{"walls":[160,160],"realWalls":[true,false],"utils":[{"Pos":54,"Wall":0,"Tag":"ventilation","Id":0},{"Pos":-1,"Wall":-1,"Tag":"canalization","Id":1},{"Pos":-1,"Wall":-1,"Tag":"window","Id":2},{"Pos":0,"Wall":0,"Tag":"entry","Id":3},{"Pos":-1,"Wall":-1,"Tag":"exit","Id":4}]},"output":[{"type":"C","subType":1,"wall":0,"width":60,"pos":0},{"type":"P","subType":0,"wall":0,"width":40,"pos":60},{"type":"W","subType":2,"wall":0,"width":60,"pos":100}]},{"input":{"walls":[180,180],"realWalls":[true,false],"utils":[{"Pos":21,"Wall":0,"Tag":"ventilation","Id":0},{"Pos":53,"Wall":0,"Tag":"canalization","Id":1},{"Pos":93,"Wall":0,"Tag":"window","Id":2},{"Pos":0,"Wall":0,"Tag":"entry","Id":3},{"Pos":180,"Wall":0,"Tag":"exit","Id":4}]},"output":[{"type":"S","subType":1,"wall":0,"width":0,"pos":0},{"type":"W","subType":2,"wall":0,"width":60,"pos":0},{"type":"C","subType":1,"wall":0,"width":60,"pos":60},{"type":"P","subType":0,"wall":0,"width":60,"pos":120}]},{"input":{"walls":[162,162],"realWalls":[true,false],"utils":[{"Pos":47,"Wall":0,"Tag":"ventilation","Id":0},{"Pos":-1,"Wall":-1,"Tag":"canalization","Id":1},{"Pos":14,"Wall":0,"Tag":"window","Id":2},{"Pos":0,"Wall":0,"Tag":"entry","Id":3},{"Pos":-1,"Wall":-1,"Tag":"exit","Id":4}]},"output":[{"type":"C","subType":1,"wall":0,"width":60,"pos":0},{"type":"P","subType":0,"wall":0,"width":42,"pos":60},{"type":"W","subType":2,"wall":0,"width":60,"pos":102}]},{"input":{"walls":[315,315],"realWalls":[true,false],"utils":[{"Pos":61,"Wall":0,"Tag":"ventilation","Id":0},{"Pos":-1,"Wall":-1,"Tag":"canalization","Id":1},{"Pos":71,"Wall":0,"Tag":"window","Id":2},{"Pos":0,"Wall":0,"Tag":"entry","Id":3},{"Pos":-1,"Wall":-1,"Tag":"exit","Id":4}]},"output":[{"type":"P","subType":0,"wall":0,"width":45,"pos":0},{"type":"C","subType":2,"wall":0,"width":60,"pos":45},{"type":"W","subType":3,"wall":0,"width":120,"pos":105},{"type":"S","subType":3,"wall":0,"width":90,"pos":225}]},{"input":{"walls":[192,192],"realWalls":[true,false],"utils":[{"Pos":16,"Wall":0,"Tag":"ventilation","Id":0},{"Pos":167,"Wall":0,"Tag":"canalization","Id":1},{"Pos":146,"Wall":0,"Tag":"window","Id":2},{"Pos":0,"Wall":0,"Tag":"entry","Id":3},{"Pos":-1,"Wall":-1,"Tag":"exit","Id":4}]},"output":[{"type":"C","subType":2,"wall":0,"width":60,"pos":0},{"type":"P","subType":0,"wall":0,"width":12,"pos":60},{"type":"S","subType":1,"wall":0,"width":60,"pos":72},{"type":"W","subType":2,"wall":0,"width":60,"pos":132}]},{"input":{"walls":[448,448],"realWalls":[true,false],"utils":[{"Pos":420,"Wall":0,"Tag":"ventilation","Id":0},{"Pos":-1,"Wall":-1,"Tag":"canalization","Id":1},{"Pos":-1,"Wall":-1,"Tag":"window","Id":2},{"Pos":0,"Wall":0,"Tag":"entry","Id":3},{"Pos":-1,"Wall":-1,"Tag":"exit","Id":4}]},"output":[{"type":"S","subType":3,"wall":0,"width":90,"pos":0},{"type":"P","subType":0,"wall":0,"width":58,"pos":90},{"type":"W","subType":3,"wall":0,"width":120,"pos":148},{"type":"P","subType":0,"wall":0,"width":60,"pos":268},{"type":"C","subType":3,"wall":0,"width":120,"pos":328}]},{"input":{"walls":[389,389],"realWalls":[true,false],"utils":[{"Pos":68,"Wall":0,"Tag":"ventilation","Id":0},{"Pos":183,"Wall":0,"Tag":"canalization","Id":1},{"Pos":-1,"Wall":-1,"Tag":"window","Id":2},{"Pos":0,"Wall":0,"Tag":"entry","Id":3},{"Pos":388,"Wall":0,"Tag":"exit","Id":4}]},"output":[{"type":"P","subType":0,"wall":0,"width":60,"pos":0},{"type":"C","subType":2,"wall":0,"width":60,"pos":60},{"type":"P","subType":0,"wall":0,"width":59,"pos":120},{"type":"W","subType":3,"wall":0,"width":120,"pos":179},{"type":"S","subType":3,"wall":0,"width":90,"pos":299}]},{"input":{"walls":[421,421],"realWalls":[true,false],"utils":[{"Pos":101,"Wall":0,"Tag":"ventilation","Id":0},{"Pos":85,"Wall":0,"Tag":"canalization","Id":1},{"Pos":366,"Wall":0,"Tag":"window","Id":2},{"Pos":0,"Wall":0,"Tag":"entry","Id":3},{"Pos":421,"Wall":0,"Tag":"exit","Id":4}]},"output":[{"type":"W","subType":3,"wall":0,"width":120,"pos":0},{"type":"P","subType":0,"wall":0,"width":31,"pos":120},{"type":"S","subType":3,"wall":0,"width":90,"pos":151},{"type":"P","subType":0,"wall":0,"width":60,"pos":241},{"type":"C","subType":3,"wall":0,"width":120,"pos":301}]},{"input":{"walls":[98,98],"realWalls":[true,false],"utils":[{"Pos":9,"Wall":0,"Tag":"ventilation","Id":0},{"Pos":-1,"Wall":-1,"Tag":"canalization","Id":1},{"Pos":-1,"Wall":-1,"Tag":"window","Id":2},{"Pos":-1,"Wall":-1,"Tag":"entry","Id":3},{"Pos":-1,"Wall":-1,"Tag":"exit","Id":4}]},"output":[{"type":"C","subType":1,"wall":0,"width":60,"pos":0},{"type":"P","subType":0,"wall":0,"width":8,"pos":60},{"type":"W","subType":1,"wall":0,"width":30,"pos":68}]},{"input":{"walls":[223,223],"realWalls":[true,false],"utils":[{"Pos":-1,"Wall":-1,"Tag":"ventilation","Id":0},{"Pos":61,"Wall":0,"Tag":"canalization","Id":1},{"Pos":-1,"Wall":-1,"Tag":"window","Id":2},{"Pos":0,"Wall":0,"Tag":"entry","Id":3},{"Pos":-1,"Wall":-1,"Tag":"exit","Id":4}]},"output":[{"type":"S","subType":2,"wall":0,"width":60,"pos":0},{"type":"W","subType":2,"wall":0,"width":60,"pos":60},{"type":"P","subType":0,"wall":0,"width":43,"pos":120},{"type":"C","subType":2,"wall":0,"width":60,"pos":163}]},{"input":{"walls":[303,303],"realWalls":[true,false],"utils":[{"Pos":-1,"Wall":-1,"Tag":"ventilation","Id":0},{"Pos":114,"Wall":0,"Tag":"canalization","Id":1},{"Pos":270,"Wall":0,"Tag":"window","Id":2},{"Pos":0,"Wall":0,"Tag":"entry","Id":3},{"Pos":-1,"Wall":-1,"Tag":"exit","Id":4}]},"output":[{"type":"S","subType":3,"wall":0,"width":90,"pos":0},{"type":"W","subType":3,"wall":0,"width":120,"pos":90},{"type":"P","subType":0,"wall":0,"width":33,"pos":210},{"type":"C","subType":2,"wall":0,"width":60,"pos":243}]},{"input":{"walls":[579,579],"realWalls":[true,false],"utils":[{"Pos":21,"Wall":0,"Tag":"ventilation","Id":0},{"Pos":296,"Wall":0,"Tag":"canalization","Id":1},{"Pos":-1,"Wall":-1,"Tag":"window","Id":2},{"Pos":0,"Wall":0,"Tag":"entry","Id":3},{"Pos":-1,"Wall":-1,"Tag":"exit","Id":4}]},"output":[{"type":"C","subType":3,"wall":0,"width":120,"pos":0},{"type":"P","subType":0,"wall":0,"width":60,"pos":120},{"type":"P","subType":0,"wall":0,"width":60,"pos":180},{"type":"W","subType":3,"wall":0,"width":120,"pos":240},{"type":"P","subType":0,"wall":0,"width":39,"pos":360},{"type":"P","subType":0,"wall":0,"width":60,"pos":399},{"type":"S","subType":4,"wall":0,"width":120,"pos":459}]},{"input":{"walls":[480,480],"realWalls":[true,false],"utils":[{"Pos":261,"Wall":0,"Tag":"ventilation","Id":0},{"Pos":-1,"Wall":-1,"Tag":"canalization","Id":1},{"Pos":-1,"Wall":-1,"Tag":"window","Id":2},{"Pos":0,"Wall":0,"Tag":"entry","Id":3},{"Pos":-1,"Wall":-1,"Tag":"exit","Id":4}]},"output":[{"type":"S","subType":4,"wall":0,"width":120,"pos":0},{"type":"P","subType":0,"wall":0,"width":60,"pos":120},{"type":"C","subType":3,"wall":0,"width":120,"pos":180},{"type":"P","subType":0,"wall":0,"width":60,"pos":300},{"type":"W","subType":3,"wall":0,"width":120,"pos":360}]},{"input":{"walls":[498,498],"realWalls":[true,false],"utils":[{"Pos":142,"Wall":0,"Tag":"ventilation","Id":0},{"Pos":387,"Wall":0,"Tag":"canalization","Id":1},{"Pos":-1,"Wall":-1,"Tag":"window","Id":2},{"Pos":0,"Wall":0,"Tag":"entry","Id":3},{"Pos":-1,"Wall":-1,"Tag":"exit","Id":4}]},"output":[{"type":"S","subType":4,"wall":0,"width":120,"pos":0},{"type":"C","subType":3,"wall":0,"width":120,"pos":120},{"type":"P","subType":0,"wall":0,"width":78,"pos":240},{"type":"P","subType":0,"wall":0,"width":60,"pos":318},{"type":"W","subType":3,"wall":0,"width":120,"pos":378}]},{"input":{"walls":[511,511],"realWalls":[true,false],"utils":[{"Pos":225,"Wall":0,"Tag":"ventilation","Id":0},{"Pos":-1,"Wall":-1,"Tag":"canalization","Id":1},{"Pos":-1,"Wall":-1,"Tag":"window","Id":2},{"Pos":0,"Wall":0,"Tag":"entry","Id":3},{"Pos":-1,"Wall":-1,"Tag":"exit","Id":4}]},"output":[{"type":"S","subType":4,"wall":0,"width":120,"pos":0},{"type":"P","subType":0,"wall":0,"width":60,"pos":120},{"type":"C","subType":3,"wall":0,"width":120,"pos":180},{"type":"P","subType":0,"wall":0,"width":31,"pos":300},{"type":"P","subType":0,"wall":0,"width":60,"pos":331},{"type":"W","subType":3,"wall":0,"width":120,"pos":391}]},{"input":{"walls":[350,350],"realWalls":[true,false],"utils":[{"Pos":216,"Wall":0,"Tag":"ventilation","Id":0},{"Pos":303,"Wall":0,"Tag":"canalization","Id":1},{"Pos":-1,"Wall":-1,"Tag":"window","Id":2},{"Pos":0,"Wall":0,"Tag":"entry","Id":3},{"Pos":-1,"Wall":-1,"Tag":"exit","Id":4}]},"output":[{"type":"S","subType":3,"wall":0,"width":90,"pos":0},{"type":"P","subType":0,"wall":0,"width":80,"pos":90},{"type":"C","subType":2,"wall":0,"width":60,"pos":170},{"type":"W","subType":3,"wall":0,"width":120,"pos":230}]},{"input":{"walls":[227,227],"realWalls":[true,false],"utils":[{"Pos":60,"Wall":0,"Tag":"ventilation","Id":0},{"Pos":78,"Wall":0,"Tag":"canalization","Id":1},{"Pos":-1,"Wall":-1,"Tag":"window","Id":2},{"Pos":0,"Wall":0,"Tag":"entry","Id":3},{"Pos":-1,"Wall":-1,"Tag":"exit","Id":4}]},"output":[{"type":"C","subType":2,"wall":0,"width":60,"pos":0},{"type":"W","subType":2,"wall":0,"width":60,"pos":60},{"type":"P","subType":0,"wall":0,"width":47,"pos":120},{"type":"S","subType":2,"wall":0,"width":60,"pos":167}]},{"input":{"walls":[430,430],"realWalls":[true,false],"utils":[{"Pos":289,"Wall":0,"Tag":"ventilation","Id":0},{"Pos":116,"Wall":0,"Tag":"canalization","Id":1},{"Pos":-1,"Wall":-1,"Tag":"window","Id":2},{"Pos":0,"Wall":0,"Tag":"entry","Id":3},{"Pos":-1,"Wall":-1,"Tag":"exit","Id":4}]},"output":[{"type":"W","subType":3,"wall":0,"width":120,"pos":0},{"type":"P","subType":0,"wall":0,"width":60,"pos":120},{"type":"C","subType":3,"wall":0,"width":120,"pos":180},{"type":"P","subType":0,"wall":0,"width":40,"pos":300},{"type":"S","subType":3,"wall":0,"width":90,"pos":340}]},{"input":{"walls":[430,430],"realWalls":[true,false],"utils":[{"Pos":289,"Wall":0,"Tag":"ventilation","Id":0},{"Pos":116,"Wall":0,"Tag":"canalization","Id":1},{"Pos":-1,"Wall":-1,"Tag":"window","Id":2},{"Pos":0,"Wall":0,"Tag":"entry","Id":3},{"Pos":-1,"Wall":-1,"Tag":"exit","Id":4}]},"output":[{"type":"S","subType":3,"wall":0,"width":90,"pos":0},{"type":"W","subType":3,"wall":0,"width":120,"pos":90},{"type":"P","subType":0,"wall":0,"width":60,"pos":210},{"type":"C","subType":3,"wall":0,"width":120,"pos":270},{"type":"P","subType":0,"wall":0,"width":40,"pos":390}]},{"input":{"walls":[239,239],"realWalls":[true,false],"utils":[{"Pos":190,"Wall":0,"Tag":"ventilation","Id":0},{"Pos":49,"Wall":0,"Tag":"canalization","Id":1},{"Pos":109,"Wall":0,"Tag":"window","Id":2},{"Pos":0,"Wall":0,"Tag":"entry","Id":3},{"Pos":-1,"Wall":-1,"Tag":"exit","Id":4}]},"output":[{"type":"W","subType":2,"wall":0,"width":60,"pos":0},{"type":"P","subType":0,"wall":0,"width":59,"pos":60},{"type":"S","subType":2,"wall":0,"width":60,"pos":119},{"type":"C","subType":2,"wall":0,"width":60,"pos":179}]},{"input":{"walls":[239,239],"realWalls":[true,false],"utils":[{"Pos":190,"Wall":0,"Tag":"ventilation","Id":0},{"Pos":49,"Wall":0,"Tag":"canalization","Id":1},{"Pos":109,"Wall":0,"Tag":"window","Id":2},{"Pos":0,"Wall":0,"Tag":"entry","Id":3},{"Pos":-1,"Wall":-1,"Tag":"exit","Id":4}]},"output":[{"type":"W","subType":2,"wall":0,"width":60,"pos":0},{"type":"P","subType":0,"wall":0,"width":59,"pos":60},{"type":"S","subType":2,"wall":0,"width":60,"pos":119},{"type":"C","subType":2,"wall":0,"width":60,"pos":179}]},{"input":{"walls":[121,121],"realWalls":[true,false],"utils":[{"Pos":103,"Wall":0,"Tag":"ventilation","Id":0},{"Pos":76,"Wall":0,"Tag":"canalization","Id":1},{"Pos":-1,"Wall":-1,"Tag":"window","Id":2},{"Pos":0,"Wall":0,"Tag":"entry","Id":3},{"Pos":120,"Wall":0,"Tag":"exit","Id":4}]},"output":[{"type":"P","subType":0,"wall":0,"width":1,"pos":0},{"type":"C","subType":1,"wall":0,"width":60,"pos":1},{"type":"W","subType":2,"wall":0,"width":60,"pos":61}]},{"input":{"walls":[292,292],"realWalls":[true,false],"utils":[{"Pos":256,"Wall":0,"Tag":"ventilation","Id":0},{"Pos":56,"Wall":0,"Tag":"canalization","Id":1},{"Pos":-1,"Wall":-1,"Tag":"window","Id":2},{"Pos":0,"Wall":0,"Tag":"entry","Id":3},{"Pos":-1,"Wall":-1,"Tag":"exit","Id":4}]},"output":[{"type":"W","subType":2,"wall":0,"width":60,"pos":0},{"type":"P","subType":0,"wall":0,"width":52,"pos":60},{"type":"S","subType":2,"wall":0,"width":60,"pos":112},{"type":"P","subType":0,"wall":0,"width":60,"pos":172},{"type":"C","subType":2,"wall":0,"width":60,"pos":232}]}]