[{"input":{"walls":[541,541],"realWalls":[true,false],"utils":[{"Pos":-1,"Wall":-1,"Tag":"ventilation","Id":0},{"Pos":486,"Wall":0,"Tag":"canalization","Id":1},{"Pos":-1,"Wall":-1,"Tag":"window","Id":2},{"Pos":0,"Wall":0,"Tag":"entry","Id":3},{"Pos":-1,"Wall":-1,"Tag":"exit","Id":4}]},"output":[{"type":"S","subType":4,"wall":0,"width":120,"pos":0},{"type":"P","subType":0,"wall":0,"width":61,"pos":120},{"type":"C","subType":3,"wall":0,"width":120,"pos":181},{"type":"P","subType":0,"wall":0,"width":60,"pos":301},{"type":"P","subType":0,"wall":0,"width":60,"pos":361},{"type":"W","subType":3,"wall":0,"width":120,"pos":421}]},{"input":{"walls":[538,538],"realWalls":[true,false],"utils":[{"Pos":-1,"Wall":-1,"Tag":"ventilation","Id":0},{"Pos":291,"Wall":0,"Tag":"canalization","Id":1},{"Pos":252,"Wall":0,"Tag":"window","Id":2},{"Pos":0,"Wall":0,"Tag":"entry","Id":3},{"Pos":-1,"Wall":-1,"Tag":"exit","Id":4}]},"output":[{"type":"P","subType":0,"wall":0,"width":60,"pos":0},{"type":"P","subType":0,"wall":0,"width":60,"pos":60},{"type":"C","subType":3,"wall":0,"width":120,"pos":120},{"type":"W","subType":3,"wall":0,"width":120,"pos":240},{"type":"P","subType":0,"wall":0,"width":58,"pos":360},{"type":"S","subType":4,"wall":0,"width":120,"pos":418}]},{"input":{"walls":[117,117],"realWalls":[true,false],"utils":[{"Pos":102,"Wall":0,"Tag":"ventilation","Id":0},{"Pos":91,"Wall":0,"Tag":"canalization","Id":1},{"Pos":20,"Wall":0,"Tag":"window","Id":2},{"Pos":0,"Wall":0,"Tag":"entry","Id":3},{"Pos":-1,"Wall":-1,"Tag":"exit","Id":4}]},"output":[{"type":"C","subType":1,"wall":0,"width":60,"pos":0},{"type":"P","subType":0,"wall":0,"width":27,"pos":60},{"type":"W","subType":1,"wall":0,"width":30,"pos":87}]},{"input":{"walls":[194,194],"realWalls":[true,false],"utils":[{"Pos":129,"Wall":0,"Tag":"ventilation","Id":0},{"Pos":20,"Wall":0,"Tag":"canalization","Id":1},{"Pos":186,"Wall":0,"Tag":"window","Id":2},{"Pos":0,"Wall":0,"Tag":"entry","Id":3},{"Pos":-1,"Wall":-1,"Tag":"exit","Id":4}]},"output":[{"type":"W","subType":2,"wall":0,"width":60,"pos":0},{"type":"S","subType":1,"wall":0,"width":60,"pos":60},{"type":"C","subType":2,"wall":0,"width":60,"pos":120},{"type":"P","subType":0,"wall":0,"width":14,"pos":180}]},{"input":{"walls":[298,298],"realWalls":[true,false],"utils":[{"Pos":-1,"Wall":-1,"Tag":"ventilation","Id":0},{"Pos":-1,"Wall":-1,"Tag":"canalization","Id":1},{"Pos":-1,"Wall":-1,"Tag":"window","Id":2},{"Pos":-1,"Wall":-1,"Tag":"entry","Id":3},{"Pos":297,"Wall":0,"Tag":"exit","Id":4}]},"output":[{"type":"S","subType":2,"wall":0,"width":60,"pos":0},{"type":"P","subType":0,"wall":0,"width":60,"pos":60},{"type":"W","subType":2,"wall":0,"width":60,"pos":120},{"type":"P","subType":0,"wall":0,"width":58,"pos":180},{"type":"C","subType":2,"wall":0,"width":60,"pos":238}]},{"input":{"walls":[126,126],"realWalls":[true,false],"utils":[{"Pos":77,"Wall":0,"Tag":"ventilation","Id":0},{"Pos":-1,"Wall":-1,"Tag":"canalization","Id":1},{"Pos":71,"Wall":0,"Tag":"window","Id":2},{"Pos":0,"Wall":0,"Tag":"entry","Id":3},{"Pos":-1,"Wall":-1,"Tag":"exit","Id":4}]},"output":[{"type":"W","subType":2,"wall":0,"width":60,"pos":0},{"type":"P","subType":0,"wall":0,"width":6,"pos":60},{"type":"C","subType":1,"wall":0,"width":60,"pos":66}]},{"input":{"walls":[582,582],"realWalls":[true,false],"utils":[{"Pos":422,"Wall":0,"Tag":"ventilation","Id":0},{"Pos":516,"Wall":0,"Tag":"canalization","Id":1},{"Pos":143,"Wall":0,"Tag":"window","Id":2},{"Pos":0,"Wall":0,"Tag":"entry","Id":3},{"Pos":-1,"Wall":-1,"Tag":"exit","Id":4}]},"output":[{"type":"S","subType":4,"wall":0,"width":120,"pos":0},{"type":"P","subType":0,"wall":0,"width":42,"pos":120},{"type":"P","subType":0,"wall":0,"width":60,"pos":162},{"type":"P","subType":0,"wall":0,"width":60,"pos":222},{"type":"P","subType":0,"wall":0,"width":60,"pos":282},{"type":"C","subType":3,"wall":0,"width":120,"pos":342},{"type":"W","subType":3,"wall":0,"width":120,"pos":462}]},{"input":{"walls":[199,199],"realWalls":[true,false],"utils":[{"Pos":21,"Wall":0,"Tag":"ventilation","Id":0},{"Pos":28,"Wall":0,"Tag":"canalization","Id":1},{"Pos":83,"Wall":0,"Tag":"window","Id":2},{"Pos":0,"Wall":0,"Tag":"entry","Id":3},{"Pos":-1,"Wall":-1,"Tag":"exit","Id":4}]},"output":[{"type":"W","subType":2,"wall":0,"width":60,"pos":0},{"type":"P","subType":0,"wall":0,"width":19,"pos":60},{"type":"C","subType":2,"wall":0,"width":60,"pos":79},{"type":"S","subType":1,"wall":0,"width":60,"pos":139}]},{"input":{"walls":[583,583],"realWalls":[true,false],"utils":[{"Pos":33,"Wall":0,"Tag":"ventilation","Id":0},{"Pos":78,"Wall":0,"Tag":"canalization","Id":1},{"Pos":-1,"Wall":-1,"Tag":"window","Id":2},{"Pos":0,"Wall":0,"Tag":"entry","Id":3},{"Pos":-1,"Wall":-1,"Tag":"exit","Id":4}]},"output":[{"type":"W","subType":3,"wall":0,"width":120,"pos":0},{"type":"C","subType":3,"wall":0,"width":120,"pos":120},{"type":"P","subType":0,"wall":0,"width":43,"pos":240},{"type":"P","subType":0,"wall":0,"width":60,"pos":283},{"type":"P","subType":0,"wall":0,"width":60,"pos":343},{"type":"P","subType":0,"wall":0,"width":60,"pos":403},{"type":"S","subType":4,"wall":0,"width":120,"pos":463}]},{"input":{"walls":[469,469],"realWalls":[true,false],"utils":[{"Pos":143,"Wall":0,"Tag":"ventilation","Id":0},{"Pos":333,"Wall":0,"Tag":"canalization","Id":1},{"Pos":-1,"Wall":-1,"Tag":"window","Id":2},{"Pos":0,"Wall":0,"Tag":"entry","Id":3},{"Pos":468,"Wall":0,"Tag":"exit","Id":4}]},"output":[{"type":"S","subType":4,"wall":0,"width":120,"pos":0},{"type":"C","subType":3,"wall":0,"width":120,"pos":120},{"type":"P","subType":0,"wall":0,"width":60,"pos":240},{"type":"W","subType":3,"wall":0,"width":120,"pos":300},{"type":"P","subType":0,"wall":0,"width":49,"pos":420}]},{"input":{"walls":[208,208],"realWalls":[true,false],"utils":[{"Pos":66,"Wall":0,"Tag":"ventilation","Id":0},{"Pos":56,"Wall":0,"Tag":"canalization","Id":1},{"Pos":-1,"Wall":-1,"Tag":"window","Id":2},{"Pos":0,"Wall":0,"Tag":"entry","Id":3},{"Pos":-1,"Wall":-1,"Tag":"exit","Id":4}]},"output":[{"type":"W","subType":2,"wall":0,"width":60,"pos":0},{"type":"C","subType":2,"wall":0,"width":60,"pos":60},{"type":"P","subType":0,"wall":0,"width":28,"pos":120},{"type":"S","subType":1,"wall":0,"width":60,"pos":148}]},{"input":{"walls":[456,456],"realWalls":[true,false],"utils":[{"Pos":125,"Wall":0,"Tag":"ventilation","Id":0},{"Pos":218,"Wall":0,"Tag":"canalization","Id":1},{"Pos":-1,"Wall":-1,"Tag":"window","Id":2},{"Pos":0,"Wall":0,"Tag":"entry","Id":3},{"Pos":-1,"Wall":-1,"Tag":"exit","Id":4}]},"output":[{"type":"P","subType":0,"wall":0,"width":36,"pos":0},{"type":"C","subType":3,"wall":0,"width":120,"pos":36},{"type":"P","subType":0,"wall":0,"width":60,"pos":156},{"type":"W","subType":3,"wall":0,"width":120,"pos":216},{"type":"S","subType":4,"wall":0,"width":120,"pos":336}]},{"input":{"walls":[288,288],"realWalls":[true,false],"utils":[{"Pos":-1,"Wall":-1,"Tag":"ventilation","Id":0},{"Pos":200,"Wall":0,"Tag":"canalization","Id":1},{"Pos":-1,"Wall":-1,"Tag":"window","Id":2},{"Pos":0,"Wall":0,"Tag":"entry","Id":3},{"Pos":-1,"Wall":-1,"Tag":"exit","Id":4}]},"output":[{"type":"C","subType":2,"wall":0,"width":60,"pos":0},{"type":"P","subType":0,"wall":0,"width":48,"pos":60},{"type":"P","subType":0,"wall":0,"width":60,"pos":108},{"type":"W","subType":2,"wall":0,"width":60,"pos":168},{"type":"S","subType":2,"wall":0,"width":60,"pos":228}]},{"input":{"walls":[127,127],"realWalls":[true,false],"utils":[{"Pos":126,"Wall":0,"Tag":"ventilation","Id":0},{"Pos":72,"Wall":0,"Tag":"canalization","Id":1},{"Pos":-1,"Wall":-1,"Tag":"window","Id":2},{"Pos":0,"Wall":0,"Tag":"entry","Id":3},{"Pos":-1,"Wall":-1,"Tag":"exit","Id":4}]},"output":[{"type":"P","subType":0,"wall":0,"width":7,"pos":0},{"type":"C","subType":1,"wall":0,"width":60,"pos":7},{"type":"W","subType":2,"wall":0,"width":60,"pos":67}]},{"input":{"walls":[576,576],"realWalls":[true,false],"utils":[{"Pos":-1,"Wall":-1,"Tag":"ventilation","Id":0},{"Pos":330,"Wall":0,"Tag":"canalization","Id":1},{"Pos":-1,"Wall":-1,"Tag":"window","Id":2},{"Pos":0,"Wall":0,"Tag":"entry","Id":3},{"Pos":-1,"Wall":-1,"Tag":"exit","Id":4}]},"output":[{"type":"S","subType":4,"wall":0,"width":120,"pos":0},{"type":"P","subType":0,"wall":0,"width":60,"pos":120},{"type":"P","subType":0,"wall":0,"width":60,"pos":180},{"type":"W","subType":3,"wall":0,"width":120,"pos":240},{"type":"P","subType":0,"wall":0,"width":36,"pos":360},{"type":"P","subType":0,"wall":0,"width":60,"pos":396},{"type":"C","subType":3,"wall":0,"width":120,"pos":456}]},{"input":{"walls":[309,309],"realWalls":[true,false],"utils":[{"Pos":-1,"Wall":-1,"Tag":"ventilation","Id":0},{"Pos":-1,"Wall":-1,"Tag":"canalization","Id":1},{"Pos":-1,"Wall":-1,"Tag":"window","Id":2},{"Pos":0,"Wall":0,"Tag":"entry","Id":3},{"Pos":-1,"Wall":-1,"Tag":"exit","Id":4}]},"output":[{"type":"S","subType":3,"wall":0,"width":90,"pos":0},{"type":"W","subType":3,"wall":0,"width":120,"pos":90},{"type":"P","subType":0,"wall":0,"width":39,"pos":210},{"type":"C","subType":2,"wall":0,"width":60,"pos":249}]},{"input":{"walls":[557,557],"realWalls":[true,false],"utils":[{"Pos":256,"Wall":0,"Tag":"ventilation","Id":0},{"Pos":308,"Wall":0,"Tag":"canalization","Id":1},{"Pos":-1,"Wall":-1,"Tag":"window","Id":2},{"Pos":0,"Wall":0,"Tag":"entry","Id":3},{"Pos":557,"Wall":0,"Tag":"exit","Id":4}]},"output":[{"type":"S","subType":4,"wall":0,"width":120,"pos":0},{"type":"P","subType":0,"wall":0,"width":60,"pos":120},{"type":"C","subType":3,"wall":0,"width":120,"pos":180},{"type":"W","subType":3,"wall":0,"width":120,"pos":300},{"type":"P","subType":0,"wall":0,"width":77,"pos":420},{"type":"P","subType":0,"wall":0,"width":60,"pos":497}]},{"input":{"walls":[112,112],"realWalls":[true,false],"utils":[{"Pos":13,"Wall":0,"Tag":"ventilation","Id":0},{"Pos":20,"Wall":0,"Tag":"canalization","Id":1},{"Pos":-1,"Wall":-1,"Tag":"window","Id":2},{"Pos":0,"Wall":0,"Tag":"entry","Id":3},{"Pos":-1,"Wall":-1,"Tag":"exit","Id":4}]},"output":[{"type":"W","subType":1,"wall":0,"width":30,"pos":0},{"type":"C","subType":1,"wall":0,"width":60,"pos":30},{"type":"P","subType":0,"wall":0,"width":22,"pos":90}]},{"input":{"walls":[384,384],"realWalls":[true,false],"utils":[{"Pos":336,"Wall":0,"Tag":"ventilation","Id":0},{"Pos":-1,"Wall":-1,"Tag":"canalization","Id":1},{"Pos":-1,"Wall":-1,"Tag":"window","Id":2},{"Pos":0,"Wall":0,"Tag":"entry","Id":3},{"Pos":-1,"Wall":-1,"Tag":"exit","Id":4}]},"output":[{"type":"S","subType":3,"wall":0,"width":90,"pos":0},{"type":"P","subType":0,"wall":0,"width":60,"pos":90},{"type":"W","subType":3,"wall":0,"width":120,"pos":150},{"type":"P","subType":0,"wall":0,"width":54,"pos":270},{"type":"C","subType":2,"wall":0,"width":60,"pos":324}]},{"input":{"walls":[495,495],"realWalls":[true,false],"utils":[{"Pos":441,"Wall":0,"Tag":"ventilation","Id":0},{"Pos":383,"Wall":0,"Tag":"canalization","Id":1},{"Pos":-1,"Wall":-1,"Tag":"window","Id":2},{"Pos":0,"Wall":0,"Tag":"entry","Id":3},{"Pos":-1,"Wall":-1,"Tag":"exit","Id":4}]},"output":[{"type":"S","subType":4,"wall":0,"width":120,"pos":0},{"type":"P","subType":0,"wall":0,"width":75,"pos":120},{"type":"P","subType":0,"wall":0,"width":60,"pos":195},{"type":"C","subType":3,"wall":0,"width":120,"pos":255},{"type":"W","subType":3,"wall":0,"width":120,"pos":375}]},{"input":{"walls":[495,495],"realWalls":[true,false],"utils":[{"Pos":441,"Wall":0,"Tag":"ventilation","Id":0},{"Pos":383,"Wall":0,"Tag":"canalization","Id":1},{"Pos":-1,"Wall":-1,"Tag":"window","Id":2},{"Pos":0,"Wall":0,"Tag":"entry","Id":3},{"Pos":-1,"Wall":-1,"Tag":"exit","Id":4}]},"output":[{"type":"S","subType":4,"wall":0,"width":120,"pos":0},{"type":"P","subType":0,"wall":0,"width":60,"pos":120},{"type":"P","subType":0,"wall":0,"width":75,"pos":180},{"type":"C","subType":3,"wall":0,"width":120,"pos":255},{"type":"W","subType":3,"wall":0,"width":120,"pos":375}]},{"input":{"walls":[271,271],"realWalls":[true,false],"utils":[{"Pos":128,"Wall":0,"Tag":"ventilation","Id":0},{"Pos":-1,"Wall":-1,"Tag":"canalization","Id":1},{"Pos":-1,"Wall":-1,"Tag":"window","Id":2},{"Pos":0,"Wall":0,"Tag":"entry","Id":3},{"Pos":-1,"Wall":-1,"Tag":"exit","Id":4}]},"output":[{"type":"S","subType":2,"wall":0,"width":60,"pos":0},{"type":"P","subType":0,"wall":0,"width":31,"pos":60},{"type":"C","subType":2,"wall":0,"width":60,"pos":91},{"type":"P","subType":0,"wall":0,"width":60,"pos":151},{"type":"W","subType":2,"wall":0,"width":60,"pos":211}]},{"input":{"walls":[444,444],"realWalls":[true,false],"utils":[{"Pos":299,"Wall":0,"Tag":"ventilation","Id":0},{"Pos":101,"Wall":0,"Tag":"canalization","Id":1},{"Pos":-1,"Wall":-1,"Tag":"window","Id":2},{"Pos":0,"Wall":0,"Tag":"entry","Id":3},{"Pos":-1,"Wall":-1,"Tag":"exit","Id":4}]},"output":[{"type":"S","subType":3,"wall":0,"width":90,"pos":0},{"type":"W","subType":3,"wall":0,"width":120,"pos":90},{"type":"P","subType":0,"wall":0,"width":60,"pos":210},{"type":"C","subType":3,"wall":0,"width":120,"pos":270},{"type":"P","subType":0,"wall":0,"width":54,"pos":390}]},{"input":{"walls":[276,276],"realWalls":[true,false],"utils":[{"Pos":160,"Wall":0,"Tag":"ventilation","Id":0},{"Pos":-1,"Wall":-1,"Tag":"canalization","Id":1},{"Pos":-1,"Wall":-1,"Tag":"window","Id":2},{"Pos":0,"Wall":0,"Tag":"entry","Id":3},{"Pos":-1,"Wall":-1,"Tag":"exit","Id":4}]},"output":[{"type":"S","subType":2,"wall":0,"width":60,"pos":0},{"type":"W","subType":2,"wall":0,"width":60,"pos":60},{"type":"P","subType":0,"wall":0,"width":36,"pos":120},{"type":"C","subType":2,"wall":0,"width":60,"pos":156},{"type":"P","subType":0,"wall":0,"width":60,"pos":216}]},{"input":{"walls":[553,553],"realWalls":[true,false],"utils":[{"Pos":-1,"Wall":-1,"Tag":"ventilation","Id":0},{"Pos":522,"Wall":0,"Tag":"canalization","Id":1},{"Pos":-1,"Wall":-1,"Tag":"window","Id":2},{"Pos":0,"Wall":0,"Tag":"entry","Id":3},{"Pos":-1,"Wall":-1,"Tag":"exit","Id":4}]},"output":[{"type":"S","subType":4,"wall":0,"width":120,"pos":0},{"type":"P","subType":0,"wall":0,"width":60,"pos":120},{"type":"C","subType":3,"wall":0,"width":120,"pos":180},{"type":"P","subType":0,"wall":0,"width":60,"pos":300},{"type":"P","subType":0,"wall":0,"width":73,"pos":360},{"type":"W","subType":3,"wall":0,"width":120,"pos":433}]},{"input":{"walls":[456,456],"realWalls":[true,false],"utils":[{"Pos":233,"Wall":0,"Tag":"ventilation","Id":0},{"Pos":-1,"Wall":-1,"Tag":"canalization","Id":1},{"Pos":-1,"Wall":-1,"Tag":"window","Id":2},{"Pos":0,"Wall":0,"Tag":"entry","Id":3},{"Pos":-1,"Wall":-1,"Tag":"exit","Id":4}]},"output":[{"type":"S","subType":4,"wall":0,"width":120,"pos":0},{"type":"P","subType":0,"wall":0,"width":36,"pos":120},{"type":"C","subType":3,"wall":0,"width":120,"pos":156},{"type":"P","subType":0,"wall":0,"width":60,"pos":276},{"type":"W","subType":3,"wall":0,"width":120,"pos":336}]},{"input":{"walls":[229,229],"realWalls":[true,false],"utils":[{"Pos":109,"Wall":0,"Tag":"ventilation","Id":0},{"Pos":143,"Wall":0,"Tag":"canalization","Id":1},{"Pos":-1,"Wall":-1,"Tag":"window","Id":2},{"Pos":-1,"Wall":-1,"Tag":"entry","Id":3},{"Pos":-1,"Wall":-1,"Tag":"exit","Id":4}]},"output":[{"type":"P","subType":0,"wall":0,"width":49,"pos":0},{"type":"C","subType":2,"wall":0,"width":60,"pos":49},{"type":"W","subType":2,"wall":0,"width":60,"pos":109},{"type":"S","subType":2,"wall":0,"width":60,"pos":169}]},{"input":{"walls":[458,458],"realWalls":[true,false],"utils":[{"Pos":78,"Wall":0,"Tag":"ventilation","Id":0},{"Pos":370,"Wall":0,"Tag":"canalization","Id":1},{"Pos":-1,"Wall":-1,"Tag":"window","Id":2},{"Pos":0,"Wall":0,"Tag":"entry","Id":3},{"Pos":456,"Wall":0,"Tag":"exit","Id":4}]},"output":[{"type":"C","subType":3,"wall":0,"width":120,"pos":0},{"type":"P","subType":0,"wall":0,"width":60,"pos":120},{"type":"S","subType":4,"wall":0,"width":120,"pos":180},{"type":"P","subType":0,"wall":0,"width":38,"pos":300},{"type":"W","subType":3,"wall":0,"width":120,"pos":338}]},{"input":{"walls":[356,356],"realWalls":[true,false],"utils":[{"Pos":-1,"Wall":-1,"Tag":"ventilation","Id":0},{"Pos":314,"Wall":0,"Tag":"canalization","Id":1},{"Pos":-1,"Wall":-1,"Tag":"window","Id":2},{"Pos":0,"Wall":0,"Tag":"entry","Id":3},{"Pos":-1,"Wall":-1,"Tag":"exit","Id":4}]},"output":[{"type":"S","subType":3,"wall":0,"width":90,"pos":0},{"type":"C","subType":2,"wall":0,"width":60,"pos":90},{"type":"P","subType":0,"wall":0,"width":86,"pos":150},{"type":"W","subType":3,"wall":0,"width":120,"pos":236}]},{"input":{"walls":[431,431],"realWalls":[true,false],"utils":[{"Pos":78,"Wall":0,"Tag":"ventilation","Id":0},{"Pos":113,"Wall":0,"Tag":"canalization","Id":1},{"Pos":215,"Wall":0,"Tag":"window","Id":2},{"Pos":0,"Wall":0,"Tag":"entry","Id":3},{"Pos":-1,"Wall":-1,"Tag":"exit","Id":4}]},"output":[{"type":"W","subType":3,"wall":0,"width":120,"pos":0},{"type":"P","subType":0,"wall":0,"width":60,"pos":120},{"type":"C","subType":3,"wall":0,"width":120,"pos":180},{"type":"P","subType":0,"wall":0,"width":41,"pos":300},{"type":"S","subType":3,"wall":0,"width":90,"pos":341}]},{"input":{"walls":[337,337],"realWalls":[true,false],"utils":[{"Pos":251,"Wall":0,"Tag":"ventilation","Id":0},{"Pos":-1,"Wall":-1,"Tag":"canalization","Id":1},{"Pos":-1,"Wall":-1,"Tag":"window","Id":2},{"Pos":0,"Wall":0,"Tag":"entry","Id":3},{"Pos":-1,"Wall":-1,"Tag":"exit","Id":4}]},"output":[{"type":"W","subType":3,"wall":0,"width":120,"pos":0},{"type":"P","subType":0,"wall":0,"width":67,"pos":120},{"type":"C","subType":2,"wall":0,"width":60,"pos":187},{"type":"S","subType":3,"wall":0,"width":90,"pos":247}]},{"input":{"walls":[150,150],"realWalls":[true,false],"utils":[{"Pos":117,"Wall":0,"Tag":"ventilation","Id":0},{"Pos":-1,"Wall":-1,"Tag":"canalization","Id":1},{"Pos":-1,"Wall":-1,"Tag":"window","Id":2},{"Pos":0,"Wall":0,"Tag":"entry","Id":3},{"Pos":150,"Wall":0,"Tag":"exit","Id":4}]},"output":[{"type":"W","subType":2,"wall":0,"width":60,"pos":0},{"type":"P","subType":0,"wall":0,"width":30,"pos":60},{"type":"C","subType":1,"wall":0,"width":60,"pos":90}]},{"input":{"walls":[473,473],"realWalls":[true,false],"utils":[{"Pos":-1,"Wall":-1,"Tag":"ventilation","Id":0},{"Pos":-1,"Wall":-1,"Tag":"canalization","Id":1},{"Pos":-1,"Wall":-1,"Tag":"window","Id":2},{"Pos":0,"Wall":0,"Tag":"entry","Id":3},{"Pos":-1,"Wall":-1,"Tag":"exit","Id":4}]},"output":[{"type":"S","subType":4,"wall":0,"width":120,"pos":0},{"type":"P","subType":0,"wall":0,"width":53,"pos":120},{"type":"W","subType":3,"wall":0,"width":120,"pos":173},{"type":"P","subType":0,"wall":0,"width":60,"pos":293},{"type":"C","subType":3,"wall":0,"width":120,"pos":353}]},{"input":{"walls":[235,235],"realWalls":[true,false],"utils":[{"Pos":-1,"Wall":-1,"Tag":"ventilation","Id":0},{"Pos":217,"Wall":0,"Tag":"canalization","Id":1},{"Pos":46,"Wall":0,"Tag":"window","Id":2},{"Pos":0,"Wall":0,"Tag":"entry","Id":3},{"Pos":-1,"Wall":-1,"Tag":"exit","Id":4}]},"output":[{"type":"C","subType":2,"wall":0,"width":60,"pos":0},{"type":"P","subType":0,"wall":0,"width":55,"pos":60},{"type":"S","subType":2,"wall":0,"width":60,"pos":115},{"type":"W","subType":2,"wall":0,"width":60,"pos":175}]},{"input":{"walls":[279,279],"realWalls":[true,false],"utils":[{"Pos":158,"Wall":0,"Tag":"ventilation","Id":0},{"Pos":153,"Wall":0,"Tag":"canalization","Id":1},{"Pos":-1,"Wall":-1,"Tag":"window","Id":2},{"Pos":0,"Wall":0,"Tag":"entry","Id":3},{"Pos":277,"Wall":0,"Tag":"exit","Id":4}]},"output":[{"type":"S","subType":2,"wall":0,"width":60,"pos":0},{"type":"P","subType":0,"wall":0,"width":39,"pos":60},{"type":"W","subType":2,"wall":0,"width":60,"pos":99},{"type":"C","subType":2,"wall":0,"width":60,"pos":159},{"type":"P","subType":0,"wall":0,"width":60,"pos":219}]},{"input":{"walls":[108,108],"realWalls":[true,false],"utils":[{"Pos":-1,"Wall":-1,"Tag":"ventilation","Id":0},{"Pos":76,"Wall":0,"Tag":"canalization","Id":1},{"Pos":96,"Wall":0,"Tag":"window","Id":2},{"Pos":0,"Wall":0,"Tag":"entry","Id":3},{"Pos":-1,"Wall":-1,"Tag":"exit","Id":4}]},"output":[{"type":"C","subType":1,"wall":0,"width":60,"pos":0},{"type":"W","subType":1,"wall":0,"width":30,"pos":60},{"type":"P","subType":0,"wall":0,"width":18,"pos":90}]},{"input":{"walls":[465,465],"realWalls":[true,false],"utils":[{"Pos":-1,"Wall":-1,"Tag":"ventilation","Id":0},{"Pos":293,"Wall":0,"Tag":"canalization","Id":1},{"Pos":-1,"Wall":-1,"Tag":"window","Id":2},{"Pos":0,"Wall":0,"Tag":"entry","Id":3},{"Pos":465,"Wall":0,"Tag":"exit","Id":4}]},"output":[{"type":"S","subType":4,"wall":0,"width":120,"pos":0},{"type":"P","subType":0,"wall":0,"width":60,"pos":120},{"type":"W","subType":3,"wall":0,"width":120,"pos":180},{"type":"P","subType":0,"wall":0,"width":45,"pos":300},{"type":"C","subType":3,"wall":0,"width":120,"pos":345}]},{"input":{"walls":[154,154],"realWalls":[true,false],"utils":[{"Pos":13,"Wall":0,"Tag":"ventilation","Id":0},{"Pos":26,"Wall":0,"Tag":"canalization","Id":1},{"Pos":-1,"Wall":-1,"Tag":"window","Id":2},{"Pos":0,"Wall":0,"Tag":"entry","Id":3},{"Pos":-1,"Wall":-1,"Tag":"exit","Id":4}]},"output":[{"type":"W","subType":2,"wall":0,"width":60,"pos":0},{"type":"C","subType":1,"wall":0,"width":60,"pos":60},{"type":"P","subType":0,"wall":0,"width":34,"pos":120}]},{"input":{"walls":[150,150],"realWalls":[true,false],"utils":[{"Pos":136,"Wall":0,"Tag":"ventilation","Id":0},{"Pos":126,"Wall":0,"Tag":"canalization","Id":1},{"Pos":-1,"Wall":-1,"Tag":"window","Id":2},{"Pos":0,"Wall":0,"Tag":"entry","Id":3},{"Pos":-1,"Wall":-1,"Tag":"exit","Id":4}]},"output":[{"type":"P","subType":0,"wall":0,"width":30,"pos":0},{"type":"C","subType":1,"wall":0,"width":60,"pos":30},{"type":"W","subType":2,"wall":0,"width":60,"pos":90}]},{"input":{"walls":[179,179],"realWalls":[true,false],"utils":[{"Pos":17,"Wall":0,"Tag":"ventilation","Id":0},{"Pos":157,"Wall":0,"Tag":"canalization","Id":1},{"Pos":47,"Wall":0,"Tag":"window","Id":2},{"Pos":0,"Wall":0,"Tag":"entry","Id":3},{"Pos":178,"Wall":0,"Tag":"exit","Id":4}]},"output":[{"type":"C","subType":1,"wall":0,"width":60,"pos":0},{"type":"P","subType":0,"wall":0,"width":59,"pos":60},{"type":"W","subType":2,"wall":0,"width":60,"pos":119}]},{"input":{"walls":[529,529],"realWalls":[true,false],"utils":[{"Pos":-1,"Wall":-1,"Tag":"ventilation","Id":0},{"Pos":491,"Wall":0,"Tag":"canalization","Id":1},{"Pos":-1,"Wall":-1,"Tag":"window","Id":2},{"Pos":0,"Wall":0,"Tag":"entry","Id":3},{"Pos":-1,"Wall":-1,"Tag":"exit","Id":4}]},"output":[{"type":"S","subType":4,"wall":0,"width":120,"pos":0},{"type":"P","subType":0,"wall":0,"width":60,"pos":120},{"type":"C","subType":3,"wall":0,"width":120,"pos":180},{"type":"P","subType":0,"wall":0,"width":60,"pos":300},{"type":"P","subType":0,"wall":0,"width":49,"pos":360},{"type":"W","subType":3,"wall":0,"width":120,"pos":409}]},{"input":{"walls":[302,302],"realWalls":[true,false],"utils":[{"Pos":-1,"Wall":-1,"Tag":"ventilation","Id":0},{"Pos":31,"Wall":0,"Tag":"canalization","Id":1},{"Pos":-1,"Wall":-1,"Tag":"window","Id":2},{"Pos":0,"Wall":0,"Tag":"entry","Id":3},{"Pos":-1,"Wall":-1,"Tag":"exit","Id":4}]},"output":[{"type":"W","subType":3,"wall":0,"width":120,"pos":0},{"type":"P","subType":0,"wall":0,"width":32,"pos":120},{"type":"C","subType":2,"wall":0,"width":60,"pos":152},{"type":"S","subType":3,"wall":0,"width":90,"pos":212}]},{"input":{"walls":[167,167],"realWalls":[true,false],"utils":[{"Pos":-1,"Wall":-1,"Tag":"ventilation","Id":0},{"Pos":-1,"Wall":-1,"Tag":"canalization","Id":1},{"Pos":24,"Wall":0,"Tag":"window","Id":2},{"Pos":0,"Wall":0,"Tag":"entry","Id":3},{"Pos":166,"Wall":0,"Tag":"exit","Id":4}]},"output":[{"type":"C","subType":1,"wall":0,"width":60,"pos":0},{"type":"P","subType":0,"wall":0,"width":47,"pos":60},{"type":"W","subType":2,"wall":0,"width":60,"pos":107}]},{"input":{"walls":[113,113],"realWalls":[true,false],"utils":[{"Pos":45,"Wall":0,"Tag":"ventilation","Id":0},{"Pos":69,"Wall":0,"Tag":"canalization","Id":1},{"Pos":-1,"Wall":-1,"Tag":"window","Id":2},{"Pos":-1,"Wall":-1,"Tag":"entry","Id":3},{"Pos":113,"Wall":0,"Tag":"exit","Id":4}]},"output":[{"type":"C","subType":1,"wall":0,"width":60,"pos":0},{"type":"W","subType":1,"wall":0,"width":30,"pos":60},{"type":"P","subType":0,"wall":0,"width":23,"pos":90}]},{"input":{"walls":[357,357],"realWalls":[true,false],"utils":[{"Pos":230,"Wall":0,"Tag":"ventilation","Id":0},{"Pos":271,"Wall":0,"Tag":"canalization","Id":1},{"Pos":283,"Wall":0,"Tag":"window","Id":2},{"Pos":0,"Wall":0,"Tag":"entry","Id":3},{"Pos":-1,"Wall":-1,"Tag":"exit","Id":4}]},"output":[{"type":"S","subType":3,"wall":0,"width":90,"pos":0},{"type":"P","subType":0,"wall":0,"width":87,"pos":90},{"type":"C","subType":2,"wall":0,"width":60,"pos":177},{"type":"W","subType":3,"wall":0,"width":120,"pos":237}]},{"input":{"walls":[521,521],"realWalls":[true,false],"utils":[{"Pos":-1,"Wall":-1,"Tag":"ventilation","Id":0},{"Pos":435,"Wall":0,"Tag":"canalization","Id":1},{"Pos":-1,"Wall":-1,"Tag":"window","Id":2},{"Pos":0,"Wall":0,"Tag":"entry","Id":3},{"Pos":520,"Wall":0,"Tag":"exit","Id":4}]},"output":[{"type":"S","subType":4,"wall":0,"width":120,"pos":0},{"type":"P","subType":0,"wall":0,"width":60,"pos":120},{"type":"C","subType":3,"wall":0,"width":120,"pos":180},{"type":"P","subType":0,"wall":0,"width":41,"pos":300},{"type":"P","subType":0,"wall":0,"width":60,"pos":341},{"type":"W","subType":3,"wall":0,"width":120,"pos":401}]},{"input":{"walls":[396,396],"realWalls":[true,false],"utils":[{"Pos":388,"Wall":0,"Tag":"ventilation","Id":0},{"Pos":48,"Wall":0,"Tag":"canalization","Id":1},{"Pos":-1,"Wall":-1,"Tag":"window","Id":2},{"Pos":0,"Wall":0,"Tag":"entry","Id":3},{"Pos":396,"Wall":0,"Tag":"exit","Id":4}]},"output":[{"type":"W","subType":3,"wall":0,"width":120,"pos":0},{"type":"P","subType":0,"wall":0,"width":60,"pos":120},{"type":"S","subType":3,"wall":0,"width":90,"pos":180},{"type":"P","subType":0,"wall":0,"width":66,"pos":270},{"type":"C","subType":2,"wall":0,"width":60,"pos":336}]},{"input":{"walls":[427,427],"realWalls":[true,false],"utils":[{"Pos":-1,"Wall":-1,"Tag":"ventilation","Id":0},{"Pos":232,"Wall":0,"Tag":"canalization","Id":1},{"Pos":-1,"Wall":-1,"Tag":"window","Id":2},{"Pos":0,"Wall":0,"Tag":"entry","Id":3},{"Pos":426,"Wall":0,"Tag":"exit","Id":4}]},"output":[{"type":"S","subType":3,"wall":0,"width":90,"pos":0},{"type":"P","subType":0,"wall":0,"width":37,"pos":90},{"type":"W","subType":3,"wall":0,"width":120,"pos":127},{"type":"P","subType":0,"wall":0,"width":60,"pos":247},{"type":"C","subType":3,"wall":0,"width":120,"pos":307}]},{"input":{"walls":[393,393],"realWalls":[true,false],"utils":[{"Pos":-1,"Wall":-1,"Tag":"ventilation","Id":0},{"Pos":31,"Wall":0,"Tag":"canalization","Id":1},{"Pos":-1,"Wall":-1,"Tag":"window","Id":2},{"Pos":0,"Wall":0,"Tag":"entry","Id":3},{"Pos":-1,"Wall":-1,"Tag":"exit","Id":4}]},"output":[{"type":"W","subType":3,"wall":0,"width":120,"pos":0},{"type":"P","subType":0,"wall":0,"width":63,"pos":120},{"type":"C","subType":2,"wall":0,"width":60,"pos":183},{"type":"P","subType":0,"wall":0,"width":60,"pos":243},{"type":"S","subType":3,"wall":0,"width":90,"pos":303}]},{"input":{"walls":[343,343],"realWalls":[true,false],"utils":[{"Pos":91,"Wall":0,"Tag":"ventilation","Id":0},{"Pos":131,"Wall":0,"Tag":"canalization","Id":1},{"Pos":278,"Wall":0,"Tag":"window","Id":2},{"Pos":0,"Wall":0,"Tag":"entry","Id":3},{"Pos":341,"Wall":0,"Tag":"exit","Id":4}]},"output":[{"type":"S","subType":3,"wall":0,"width":90,"pos":0},{"type":"W","subType":3,"wall":0,"width":120,"pos":90},{"type":"P","subType":0,"wall":0,"width":73,"pos":210},{"type":"C","subType":2,"wall":0,"width":60,"pos":283}]},{"input":{"walls":[555,555],"realWalls":[true,false],"utils":[{"Pos":-1,"Wall":-1,"Tag":"ventilation","Id":0},{"Pos":378,"Wall":0,"Tag":"canalization","Id":1},{"Pos":-1,"Wall":-1,"Tag":"window","Id":2},{"Pos":0,"Wall":0,"Tag":"entry","Id":3},{"Pos":-1,"Wall":-1,"Tag":"exit","Id":4}]},"output":[{"type":"C","subType":3,"wall":0,"width":120,"pos":0},{"type":"P","subType":0,"wall":0,"width":60,"pos":120},{"type":"P","subType":0,"wall":0,"width":60,"pos":180},{"type":"P","subType":0,"wall":0,"width":75,"pos":240},{"type":"W","subType":3,"wall":0,"width":120,"pos":315},{"type":"S","subType":4,"wall":0,"width":120,"pos":435}]},{"input":{"walls":[419,419],"realWalls":[true,false],"utils":[{"Pos":-1,"Wall":-1,"Tag":"ventilation","Id":0},{"Pos":279,"Wall":0,"Tag":"canalization","Id":1},{"Pos":-1,"Wall":-1,"Tag":"window","Id":2},{"Pos":0,"Wall":0,"Tag":"entry","Id":3},{"Pos":-1,"Wall":-1,"Tag":"exit","Id":4}]},"output":[{"type":"S","subType":3,"wall":0,"width":90,"pos":0},{"type":"P","subType":0,"wall":0,"width":89,"pos":90},{"type":"W","subType":3,"wall":0,"width":120,"pos":179},{"type":"P","subType":0,"wall":0,"width":60,"pos":299},{"type":"C","subType":2,"wall":0,"width":60,"pos":359}]},{"input":{"walls":[239,239],"realWalls":[true,false],"utils":[{"Pos":220,"Wall":0,"Tag":"ventilation","Id":0},{"Pos":-1,"Wall":-1,"Tag":"canalization","Id":1},{"Pos":-1,"Wall":-1,"Tag":"window","Id":2},{"Pos":0,"Wall":0,"Tag":"entry","Id":3},{"Pos":-1,"Wall":-1,"Tag":"exit","Id":4}]},"output":[{"type":"S","subType":2,"wall":0,"width":60,"pos":0},{"type":"W","subType":2,"wall":0,"width":60,"pos":60},{"type":"P","subType":0,"wall":0,"width":59,"pos":120},{"type":"C","subType":2,"wall":0,"width":60,"pos":179}]},{"input":{"walls":[400,400],"realWalls":[true,false],"utils":[{"Pos":336,"Wall":0,"Tag":"ventilation","Id":0},{"Pos":341,"Wall":0,"Tag":"canalization","Id":1},{"Pos":238,"Wall":0,"Tag":"window","Id":2},{"Pos":0,"Wall":0,"Tag":"entry","Id":3},{"Pos":398,"Wall":0,"Tag":"exit","Id":4}]},"output":[{"type":"S","subType":3,"wall":0,"width":90,"pos":0},{"type":"P","subType":0,"wall":0,"width":70,"pos":90},{"type":"P","subType":0,"wall":0,"width":60,"pos":160},{"type":"C","subType":2,"wall":0,"width":60,"pos":220},{"type":"W","subType":3,"wall":0,"width":120,"pos":280}]},{"input":{"walls":[494,494],"realWalls":[true,false],"utils":[{"Pos":375,"Wall":0,"Tag":"ventilation","Id":0},{"Pos":246,"Wall":0,"Tag":"canalization","Id":1},{"Pos":-1,"Wall":-1,"Tag":"window","Id":2},{"Pos":0,"Wall":0,"Tag":"entry","Id":3},{"Pos":493,"Wall":0,"Tag":"exit","Id":4}]},"output":[{"type":"S","subType":4,"wall":0,"width":120,"pos":0},{"type":"P","subType":0,"wall":0,"width":60,"pos":120},{"type":"W","subType":3,"wall":0,"width":120,"pos":180},{"type":"P","subType":0,"wall":0,"width":74,"pos":300},{"type":"C","subType":3,"wall":0,"width":120,"pos":374}]},{"input":{"walls":[426,426],"realWalls":[true,false],"utils":[{"Pos":-1,"Wall":-1,"Tag":"ventilation","Id":0},{"Pos":247,"Wall":0,"Tag":"canalization","Id":1},{"Pos":-1,"Wall":-1,"Tag":"window","Id":2},{"Pos":0,"Wall":0,"Tag":"entry","Id":3},{"Pos":-1,"Wall":-1,"Tag":"exit","Id":4}]},"output":[{"type":"S","subType":3,"wall":0,"width":90,"pos":0},{"type":"P","subType":0,"wall":0,"width":60,"pos":90},{"type":"W","subType":3,"wall":0,"width":120,"pos":150},{"type":"P","subType":0,"wall":0,"width":36,"pos":270},{"type":"C","subType":3,"wall":0,"width":120,"pos":306}]},{"input":{"walls":[452,452],"realWalls":[true,false],"utils":[{"Pos":146,"Wall":0,"Tag":"ventilation","Id":0},{"Pos":-1,"Wall":-1,"Tag":"canalization","Id":1},{"Pos":-1,"Wall":-1,"Tag":"window","Id":2},{"Pos":0,"Wall":0,"Tag":"entry","Id":3},{"Pos":451,"Wall":0,"Tag":"exit","Id":4}]},"output":[{"type":"S","subType":4,"wall":0,"width":120,"pos":0},{"type":"C","subType":3,"wall":0,"width":120,"pos":120},{"type":"P","subType":0,"wall":0,"width":60,"pos":240},{"type":"P","subType":0,"wall":0,"width":32,"pos":300},{"type":"W","subType":3,"wall":0,"width":120,"pos":332}]},{"input":{"walls":[500,500],"realWalls":[true,false],"utils":[{"Pos":408,"Wall":0,"Tag":"ventilation","Id":0},{"Pos":363,"Wall":0,"Tag":"canalization","Id":1},{"Pos":-1,"Wall":-1,"Tag":"window","Id":2},{"Pos":0,"Wall":0,"Tag":"entry","Id":3},{"Pos":-1,"Wall":-1,"Tag":"exit","Id":4}]},"output":[{"type":"S","subType":4,"wall":0,"width":120,"pos":0},{"type":"P","subType":0,"wall":0,"width":80,"pos":120},{"type":"P","subType":0,"wall":0,"width":60,"pos":200},{"type":"W","subType":3,"wall":0,"width":120,"pos":260},{"type":"C","subType":3,"wall":0,"width":120,"pos":380}]},{"input":{"walls":[169,169],"realWalls":[true,false],"utils":[{"Pos":118,"Wall":0,"Tag":"ventilation","Id":0},{"Pos":77,"Wall":0,"Tag":"canalization","Id":1},{"Pos":90,"Wall":0,"Tag":"window","Id":2},{"Pos":0,"Wall":0,"Tag":"entry","Id":3},{"Pos":169,"Wall":0,"Tag":"exit","Id":4}]},"output":[{"type":"P","subType":0,"wall":0,"width":49,"pos":0},{"type":"W","subType":2,"wall":0,"width":60,"pos":49},{"type":"C","subType":1,"wall":0,"width":60,"pos":109}]},{"input":{"walls":[331,331],"realWalls":[true,false],"utils":[{"Pos":220,"Wall":0,"Tag":"ventilation","Id":0},{"Pos":7,"Wall":0,"Tag":"canalization","Id":1},{"Pos":190,"Wall":0,"Tag":"window","Id":2},{"Pos":0,"Wall":0,"Tag":"entry","Id":3},{"Pos":331,"Wall":0,"Tag":"exit","Id":4}]},"output":[{"type":"W","subType":3,"wall":0,"width":120,"pos":0},{"type":"P","subType":0,"wall":0,"width":61,"pos":120},{"type":"C","subType":2,"wall":0,"width":60,"pos":181},{"type":"S","subType":3,"wall":0,"width":90,"pos":241}]},{"input":{"walls":[489,489],"realWalls":[true,false],"utils":[{"Pos":-1,"Wall":-1,"Tag":"ventilation","Id":0},{"Pos":474,"Wall":0,"Tag":"canalization","Id":1},{"Pos":-1,"Wall":-1,"Tag":"window","Id":2},{"Pos":0,"Wall":0,"Tag":"entry","Id":3},{"Pos":-1,"Wall":-1,"Tag":"exit","Id":4}]},"output":[{"type":"S","subType":4,"wall":0,"width":120,"pos":0},{"type":"P","subType":0,"wall":0,"width":60,"pos":120},{"type":"C","subType":3,"wall":0,"width":120,"pos":180},{"type":"P","subType":0,"wall":0,"width":69,"pos":300},{"type":"W","subType":3,"wall":0,"width":120,"pos":369}]},{"input":{"walls":[414,414],"realWalls":[true,false],"utils":[{"Pos":-1,"Wall":-1,"Tag":"ventilation","Id":0},{"Pos":57,"Wall":0,"Tag":"canalization","Id":1},{"Pos":-1,"Wall":-1,"Tag":"window","Id":2},{"Pos":-1,"Wall":-1,"Tag":"entry","Id":3},{"Pos":-1,"Wall":-1,"Tag":"exit","Id":4}]},"output":[{"type":"W","subType":3,"wall":0,"width":120,"pos":0},{"type":"P","subType":0,"wall":0,"width":84,"pos":120},{"type":"C","subType":2,"wall":0,"width":60,"pos":204},{"type":"P","subType":0,"wall":0,"width":60,"pos":264},{"type":"S","subType":3,"wall":0,"width":90,"pos":324}]},{"input":{"walls":[199,199],"realWalls":[true,false],"utils":[{"Pos":23,"Wall":0,"Tag":"ventilation","Id":0},{"Pos":83,"Wall":0,"Tag":"canalization","Id":1},{"Pos":-1,"Wall":-1,"Tag":"window","Id":2},{"Pos":0,"Wall":0,"Tag":"entry","Id":3},{"Pos":-1,"Wall":-1,"Tag":"exit","Id":4}]},"output":[{"type":"C","subType":2,"wall":0,"width":60,"pos":0},{"type":"P","subType":0,"wall":0,"width":19,"pos":60},{"type":"W","subType":2,"wall":0,"width":60,"pos":79},{"type":"S","subType":1,"wall":0,"width":60,"pos":139}]},{"input":{"walls":[342,342],"realWalls":[true,false],"utils":[{"Pos":111,"Wall":0,"Tag":"ventilation","Id":0},{"Pos":106,"Wall":0,"Tag":"canalization","Id":1},{"Pos":-1,"Wall":-1,"Tag":"window","Id":2},{"Pos":0,"Wall":0,"Tag":"entry","Id":3},{"Pos":-1,"Wall":-1,"Tag":"exit","Id":4}]},"output":[{"type":"W","subType":3,"wall":0,"width":120,"pos":0},{"type":"C","subType":2,"wall":0,"width":60,"pos":120},{"type":"P","subType":0,"wall":0,"width":72,"pos":180},{"type":"S","subType":3,"wall":0,"width":90,"pos":252}]},{"input":{"walls":[344,344],"realWalls":[true,false],"utils":[{"Pos":-1,"Wall":-1,"Tag":"ventilation","Id":0},{"Pos":311,"Wall":0,"Tag":"canalization","Id":1},{"Pos":-1,"Wall":-1,"Tag":"window","Id":2},{"Pos":0,"Wall":0,"Tag":"entry","Id":3},{"Pos":343,"Wall":0,"Tag":"exit","Id":4}]},"output":[{"type":"S","subType":3,"wall":0,"width":90,"pos":0},{"type":"C","subType":2,"wall":0,"width":60,"pos":90},{"type":"P","subType":0,"wall":0,"width":74,"pos":150},{"type":"W","subType":3,"wall":0,"width":120,"pos":224}]},{"input":{"walls":[386,386],"realWalls":[true,false],"utils":[{"Pos":-1,"Wall":-1,"Tag":"ventilation","Id":0},{"Pos":101,"Wall":0,"Tag":"canalization","Id":1},{"Pos":-1,"Wall":-1,"Tag":"window","Id":2},{"Pos":0,"Wall":0,"Tag":"entry","Id":3},{"Pos":-1,"Wall":-1,"Tag":"exit","Id":4}]},"output":[{"type":"S","subType":3,"wall":0,"width":90,"pos":0},{"type":"W","subType":3,"wall":0,"width":120,"pos":90},{"type":"P","subType":0,"wall":0,"width":60,"pos":210},{"type":"P","subType":0,"wall":0,"width":56,"pos":270},{"type":"C","subType":2,"wall":0,"width":60,"pos":326}]},{"input":{"walls":[404,404],"realWalls":[true,false],"utils":[{"Pos":181,"Wall":0,"Tag":"ventilation","Id":0},{"Pos":188,"Wall":0,"Tag":"canalization","Id":1},{"Pos":-1,"Wall":-1,"Tag":"window","Id":2},{"Pos":0,"Wall":0,"Tag":"entry","Id":3},{"Pos":-1,"Wall":-1,"Tag":"exit","Id":4}]},"output":[{"type":"S","subType":3,"wall":0,"width":90,"pos":0},{"type":"W","subType":3,"wall":0,"width":120,"pos":90},{"type":"C","subType":2,"wall":0,"width":60,"pos":210},{"type":"P","subType":0,"wall":0,"width":60,"pos":270},{"type":"P","subType":0,"wall":0,"width":74,"pos":330}]},{"input":{"walls":[207,207],"realWalls":[true,false],"utils":[{"Pos":133,"Wall":0,"Tag":"ventilation","Id":0},{"Pos":-1,"Wall":-1,"Tag":"canalization","Id":1},{"Pos":-1,"Wall":-1,"Tag":"window","Id":2},{"Pos":-1,"Wall":-1,"Tag":"entry","Id":3},{"Pos":-1,"Wall":-1,"Tag":"exit","Id":4}]},"output":[{"type":"W","subType":2,"wall":0,"width":60,"pos":0},{"type":"P","subType":0,"wall":0,"width":27,"pos":60},{"type":"C","subType":2,"wall":0,"width":60,"pos":87},{"type":"S","subType":1,"wall":0,"width":60,"pos":147}]}]